Workbook

Sheet 1and2
B2: 1 week of sale
C3: Uniform distribution | D3: 120 | E3: 420
C4: Expected sale= | D4: =AVERAGE(D3:E3) -> 270
C6: Cost=c= | D6: 3
C7: Selling price=p= | D7: $5 or $6
C8: Refund fraction= | D8: 0.5 | E8: [0.25-0.75 scenarios]
C9: Return shipping= | D9: 0.5 | E9: per unit
C10: K= | D10: 20 | E10: per order
C11: Prize value= | D11: 40000
A12: 1 | C12: Suppose selling price is $5. So Cost of Underage=5-3=$2; Cost of overage=3+0.5-3*0.5=2. So the right balance would be at the mid point and hence 270.
C13: This is because for every unit extra we don’t sell, it would cost $2 and every unit shortage we have, we loos $2 as well.
C14: We need to find the spot where P(D>=Q)=P(D<=Q)=Mean demand for the uniform distribution and in this case it is 270
C15: At $6 selling price, the custo of Underage=6-3=$3 while the cost of overage remains the same at $2. So it hurts to loose sales than have overages.
C16: So in this case, the tendence would be to keep higher stock than mid point and hence more than 270
A18: 2 | C18: At $5 selling price
B19: Co= | C19: 3-0.5*3+.5= | D19: =3-0.5*3+0.5 -> 2
B20: Cu= | C20: 5-3= | D20: =5-3 -> 2
B21: F(X*)= | C21: Cu/(Cu+Co)= | D21: =D20/(D20+D19) -> 0.5
B23: X*$5,0.5= | C23: =D21*($E$3-$D$3)+$D$3 -> 270 | D23: Expected Sales= | K23: =(270^2-120^2)/(2*300)+((420-270)*270)/300 -> 232.5
D24: Expected left over= | F24: =C23-K23 -> 37.5 | G24: a. | H24: Expected revenue= | J24: =$K23*5 -> 1162.5
G25: b. | H25: Salvage value of left over= | K25: =F24*$D$6*$D$8 -> 56.25
G26: c. | H26: Shipping cost= | J26: =F24*$D$9*-1 -> -18.75
G27: d. | H27: Ordering cost= | J27: =$D$10*-1 -> -20
G28: e. | H28: Variable buying cost= | J28: =C23*D6*-1 -> -810
I29: Expected Profit= | J29: a+b+c+d+e
I30: = | J30: =J27+J26+K25+J24+J28 -> 370
B32: Limitation of using uniform demand assumption:
B35: at $6 selling price
B36: Co= | C36: 3-0.5*3+.5= | D36: =3-0.5*3+0.5 -> 2
B37: Cu= | C37: 6-3= | D37: =6-3 -> 3
B38: F(X*)= | C38: Cu/(Cu+Co)= | D38: =D37/(D37+D36) -> 0.6
B40: X*$6,0.5= | C40: =D38*($E$3-$D$3)+$D$3 -> 300 | D40: Expected Sales= | K40: =(300^2-120^2)/(2*300)+((420-300)*300)/300 -> 246
D41: Expected left over= | F41: =C40-K40 -> 54 | G41: a. | H41: Expected revenue= | J41: =$K40*6 -> 1476
G42: b. | H42: Salvage value of left over= | K42: =F41*$D$6*$D$8 -> 81
G43: c. | H43: Shipping cost= | J43: =F41*$D$9*-1 -> -27
G44: d. | H44: Ordering cost= | J44: =$D$10*-1 -> -20
G45: e. | H45: Variable buying cost= | J45: =C40*D6*-1 -> -900
I46: Expected Profit= | J46: a+b+c+d+e
I47: = | J47: =J44+J43+K42+J41+J45 -> 610

Sheet 3
B2: 1 week of sale
C3: Uniform dist | D3: 120 | E3: 420
C4: Expected sale= | D4: =AVERAGE(D3:E3) -> 270
C6: Cost=c= | D6: 3
C7: Selling price=p= | D7: $5 or $6
C8: Refund fraction= | D8: 0.5 | E8: [0.25-0.75 scenarios]
C9: Return shipping= | D9: 0.5 | E9: per unit
C10: K= | D10: 20 | E10: per order
C11: Prize value= | D11: 40000
B14: at $5 selling price | D14: at 0.25 refund | F14: at 0.75 refund
B15: Co= | C15: 3-0.25*3+.5= | D15: =3-0.25*3+0.5 -> 2.75 | E15: 3-0.75*3+.5= | F15: =3-0.75*3+0.5 -> 1.25
B16: Cu= | C16: 5-3= | D16: =5-3 -> 2 | F16: =5-3 -> 2
B17: F(X*)= | C17: Cu/(Cu+Co)= | D17: =D16/(D16+D15) -> 0.42105263 | F17: =F16/(F16+F15) -> 0.61538462
D19: =D17*($E$3-$D$3)+$D$3 -> 246.31579 | F19: =F17*($E$3-$D$3)+$D$3 -> 304.61538
B20: at $6 selling price
B21: Co= | C21: 3-0.25*3+.5= | D21: =3-0.25*3+0.5 -> 2.75 | E21: 3-0.75*3+.5= | F21: =3-0.75*3+0.5 -> 1.25
B22: Cu= | C22: 6-3= | D22: =6-3 -> 3 | F22: =6-3 -> 3
B23: F(X*)= | C23: Cu/(Cu+Co)= | D23: =D22/(D22+D21) -> 0.52173913 | F23: =F22/(F22+F21) -> 0.70588235
B25: X*$6,0.25= | D25: =D23*(E3-D3)+D3 -> 276.52174 | F25: =F23*($E$3-$D$3)+$D$3 -> 331.76471

Sheet 4
B2: 1 week of sale | I2: 1 week of sale
C3: Uniform dist | D3: 120 | E3: 420 | J3: Uniform dist | K3: 120 | L3: 420
C4: Expected sale= | D4: =AVERAGE(D3:E3) -> 270 | J4: Expected sale= | K4: =AVERAGE(K3:L3) -> 270
C6: Cost=c= | D6: 3 | J6: Cost=c= | K6: 3
C7: Selling price=p= | D7: $5 or $6 | J7: Selling price=p= | K7: $5 or $6
C8: Refund fraction= | D8: 0.5 | E8: [0.25-0.75 scenarios] | J8: Refund fraction= | K8: 0.5 | L8: [0.25-0.75 scenarios]
C9: Return shipping= | D9: 0.5 | E9: per unit | J9: Return shipping= | K9: 0.5 | L9: per unit
C10: K= | D10: 20 | E10: per order | J10: K= | K10: 20 | L10: per order
C11: Prize value= | D11: 40000 | J11: Prize value= | K11: 40000
B20: at $6 selling price | D20: at 0.5 refund | I20: at $5 selling price | K20: at 0.5 refund
B21: Co= | C21: 3-0.5*3+.5= | D21: =3-0.5*3+0.5 -> 2 | I21: Co= | J21: 3-0.5*3+.5= | K21: =3-0.5*3+0.5 -> 2
B22: Cu= | C22: 6-3= | D22: =6-3 -> 3 | I22: Cu= | J22: 5-3= | K22: =5-3 -> 2
B23: F(X*)= | C23: Cu/(Cu+Co)= | D23: =D22/(D22+D21) -> 0.6 | I23: F(X*)= | J23: Cu/(Cu+Co)= | K23: =K22/(K22+K21) -> 0.5
B25: X*= | D25: =D23*(E3-D3)+D3 -> 300 | I25: X*= | K25: =K23*(L3-K3)+K3 -> 270
B26: Expected Sales= | G26: =(300^2-120^2)/(2*300)+((420-300)*300)/300 -> 246 | I26: Expected Sales= | N26: =(270^2-120^2)/(2*300)+((420-270)*270)/300 -> 232.5
B27: Expected left over= | C27: =D25-G26 -> 54 | D27: a. | E27: Expected revenue= | G27: =$G26*6 -> 1476 | I27: Expected left over= | J27: =K25-N26 -> 37.5 | K27: a. | L27: Expected revenue= | N27: =$N26*5 -> 1162.5
D28: b. | E28: Salvage value of left over= | G28: =C27*$D$6*$D$8 -> 81 | K28: b. | L28: Salvage value of left over= | N28: =J27*$D$6*$D$8 -> 56.25
D29: c. | E29: Shipping cost= | G29: =C27*$D$9*-1 -> -27 | K29: c. | L29: Shipping cost= | N29: =J27*$D$9*-1 -> -18.75
D30: d. | E30: Ordering cost= | G30: =$D$10*-1 -> -20 | K30: d. | L30: Ordering cost= | N30: =$D$10*-1 -> -20
D31: e. | E31: Variable buying cost= | G31: =-1*D25*D6 -> -900 | K31: e. | L31: Variable buying cost= | N31: =-1*K25*K6 -> -810
F32: Expected Profit= | G32: a+b+c+d+e | M32: Expected Profit= | N32: a+b+c+d+e
F33: = | G33: =G30+G29+G28+G27+G31 -> 610 | M33: = | N33: =N30+N29+N28+N27+N31 -> 370
A36: Would would happen if raising prices changes demand?

Sheet 5
B2: 1 week of sale
C3: Uniform dist | D3: 120 | E3: 420
C4: Expected sale= | D4: =AVERAGE(D3:E3) -> 270 | I4: S.no | J4: Demand | K4: Units sold | L4: Left over units | M4: Revenue | N4: Setup cost | O4: Cost - Var | P4: Cost-shipping | Q4: Refund | R4: Net Profit | S4: count of loss
I5: 1 | J5: =RANDBETWEEN(120,420) -> 127 | K5: =IF(J5>=$D$18,$D$18,J5) -> 127 | L5: =$D$18-K5 -> 143 | M5: =K5*5 -> 635 | N5: =-$D$10 -> -20 | O5: =-$D$6*$D$18 -> -810 | P5: =-L5*$D$9 -> -71.5 | Q5: =L5*($D$6*$D$8) -> 214.5 | R5: =SUM(M5:Q5) -> -52 | S5: =IF(R5<0,1,0) -> 1
C6: Cost=c= | D6: 3 | I6: =I5+1 -> 2 | J6: =RANDBETWEEN(120,420) -> 417 | K6: =IF(J6>=$D$18,$D$18,J6) -> 270 | L6: =$D$18-K6 -> 0 | M6: =K6*5 -> 1350 | N6: =-$D$10 -> -20 | O6: =-$D$6*$D$18 -> -810 | P6: =-L6*$D$9 -> 0 | Q6: =L6*($D$6*$D$8) -> 0 | R6: =SUM(M6:Q6) -> 520 | S6: =IF(R6<0,1,0) -> 0
C7: Selling price=p= | D7: $5 or $6 | I7: =I6+1 -> 3 | J7: =RANDBETWEEN(120,420) -> 274 | K7: =IF(J7>=$D$18,$D$18,J7) -> 270 | L7: =$D$18-K7 -> 0 | M7: =K7*5 -> 1350 | N7: =-$D$10 -> -20 | O7: =-$D$6*$D$18 -> -810 | P7: =-L7*$D$9 -> 0 | Q7: =L7*($D$6*$D$8) -> 0 | R7: =SUM(M7:Q7) -> 520 | S7: =IF(R7<0,1,0) -> 0
C8: Refund fraction= | D8: 0.5 | E8: [0.25-0.75 scenarios] | I8: =I7+1 -> 4 | J8: =RANDBETWEEN(120,420) -> 410 | K8: =IF(J8>=$D$18,$D$18,J8) -> 270 | L8: =$D$18-K8 -> 0 | M8: =K8*5 -> 1350 | N8: =-$D$10 -> -20 | O8: =-$D$6*$D$18 -> -810 | P8: =-L8*$D$9 -> 0 | Q8: =L8*($D$6*$D$8) -> 0 | R8: =SUM(M8:Q8) -> 520 | S8: =IF(R8<0,1,0) -> 0
C9: Return shipping= | D9: 0.5 | E9: per unit | I9: =I8+1 -> 5 | J9: =RANDBETWEEN(120,420) -> 305 | K9: =IF(J9>=$D$18,$D$18,J9) -> 270 | L9: =$D$18-K9 -> 0 | M9: =K9*5 -> 1350 | N9: =-$D$10 -> -20 | O9: =-$D$6*$D$18 -> -810 | P9: =-L9*$D$9 -> 0 | Q9: =L9*($D$6*$D$8) -> 0 | R9: =SUM(M9:Q9) -> 520 | S9: =IF(R9<0,1,0) -> 0
C10: K= | D10: 20 | E10: per order | I10: =I9+1 -> 6 | J10: =RANDBETWEEN(120,420) -> 201 | K10: =IF(J10>=$D$18,$D$18,J10) -> 201 | L10: =$D$18-K10 -> 69 | M10: =K10*5 -> 1005 | N10: =-$D$10 -> -20 | O10: =-$D$6*$D$18 -> -810 | P10: =-L10*$D$9 -> -34.5 | Q10: =L10*($D$6*$D$8) -> 103.5 | R10: =SUM(M10:Q10) -> 244 | S10: =IF(R10<0,1,0) -> 0
C11: Prize value= | D11: 40000 | I11: =I10+1 -> 7 | J11: =RANDBETWEEN(120,420) -> 356 | K11: =IF(J11>=$D$18,$D$18,J11) -> 270 | L11: =$D$18-K11 -> 0 | M11: =K11*5 -> 1350 | N11: =-$D$10 -> -20 | O11: =-$D$6*$D$18 -> -810 | P11: =-L11*$D$9 -> 0 | Q11: =L11*($D$6*$D$8) -> 0 | R11: =SUM(M11:Q11) -> 520 | S11: =IF(R11<0,1,0) -> 0
I12: =I11+1 -> 8 | J12: =RANDBETWEEN(120,420) -> 242 | K12: =IF(J12>=$D$18,$D$18,J12) -> 242 | L12: =$D$18-K12 -> 28 | M12: =K12*5 -> 1210 | N12: =-$D$10 -> -20 | O12: =-$D$6*$D$18 -> -810 | P12: =-L12*$D$9 -> -14 | Q12: =L12*($D$6*$D$8) -> 42 | R12: =SUM(M12:Q12) -> 408 | S12: =IF(R12<0,1,0) -> 0
B13: at $5 selling price | D13: at 0.5 refund | I13: =I12+1 -> 9 | J13: =RANDBETWEEN(120,420) -> 293 | K13: =IF(J13>=$D$18,$D$18,J13) -> 270 | L13: =$D$18-K13 -> 0 | M13: =K13*5 -> 1350 | N13: =-$D$10 -> -20 | O13: =-$D$6*$D$18 -> -810 | P13: =-L13*$D$9 -> 0 | Q13: =L13*($D$6*$D$8) -> 0 | R13: =SUM(M13:Q13) -> 520 | S13: =IF(R13<0,1,0) -> 0
B14: Co= | C14: 3-0.5*3+.5= | D14: =3-0.5*3+0.5 -> 2 | I14: =I13+1 -> 10 | J14: =RANDBETWEEN(120,420) -> 273 | K14: =IF(J14>=$D$18,$D$18,J14) -> 270 | L14: =$D$18-K14 -> 0 | M14: =K14*5 -> 1350 | N14: =-$D$10 -> -20 | O14: =-$D$6*$D$18 -> -810 | P14: =-L14*$D$9 -> 0 | Q14: =L14*($D$6*$D$8) -> 0 | R14: =SUM(M14:Q14) -> 520 | S14: =IF(R14<0,1,0) -> 0
B15: Cu= | C15: 5-3= | D15: =5-3 -> 2 | I15: =I14+1 -> 11 | J15: =RANDBETWEEN(120,420) -> 322 | K15: =IF(J15>=$D$18,$D$18,J15) -> 270 | L15: =$D$18-K15 -> 0 | M15: =K15*5 -> 1350 | N15: =-$D$10 -> -20 | O15: =-$D$6*$D$18 -> -810 | P15: =-L15*$D$9 -> 0 | Q15: =L15*($D$6*$D$8) -> 0 | R15: =SUM(M15:Q15) -> 520 | S15: =IF(R15<0,1,0) -> 0
B16: F(X*)= | C16: Cu/(Cu+Co)= | D16: =D15/(D15+D14) -> 0.5 | I16: =I15+1 -> 12 | J16: =RANDBETWEEN(120,420) -> 379 | K16: =IF(J16>=$D$18,$D$18,J16) -> 270 | L16: =$D$18-K16 -> 0 | M16: =K16*5 -> 1350 | N16: =-$D$10 -> -20 | O16: =-$D$6*$D$18 -> -810 | P16: =-L16*$D$9 -> 0 | Q16: =L16*($D$6*$D$8) -> 0 | R16: =SUM(M16:Q16) -> 520 | S16: =IF(R16<0,1,0) -> 0
I17: =I16+1 -> 13 | J17: =RANDBETWEEN(120,420) -> 140 | K17: =IF(J17>=$D$18,$D$18,J17) -> 140 | L17: =$D$18-K17 -> 130 | M17: =K17*5 -> 700 | N17: =-$D$10 -> -20 | O17: =-$D$6*$D$18 -> -810 | P17: =-L17*$D$9 -> -65 | Q17: =L17*($D$6*$D$8) -> 195 | R17: =SUM(M17:Q17) -> 0 | S17: =IF(R17<0,1,0) -> 0
B18: X*= | D18: =D16*(E3-D3)+D3 -> 270 | I18: =I17+1 -> 14 | J18: =RANDBETWEEN(120,420) -> 184 | K18: =IF(J18>=$D$18,$D$18,J18) -> 184 | L18: =$D$18-K18 -> 86 | M18: =K18*5 -> 920 | N18: =-$D$10 -> -20 | O18: =-$D$6*$D$18 -> -810 | P18: =-L18*$D$9 -> -43 | Q18: =L18*($D$6*$D$8) -> 129 | R18: =SUM(M18:Q18) -> 176 | S18: =IF(R18<0,1,0) -> 0
I19: =I18+1 -> 15 | J19: =RANDBETWEEN(120,420) -> 174 | K19: =IF(J19>=$D$18,$D$18,J19) -> 174 | L19: =$D$18-K19 -> 96 | M19: =K19*5 -> 870 | N19: =-$D$10 -> -20 | O19: =-$D$6*$D$18 -> -810 | P19: =-L19*$D$9 -> -48 | Q19: =L19*($D$6*$D$8) -> 144 | R19: =SUM(M19:Q19) -> 136 | S19: =IF(R19<0,1,0) -> 0
I20: =I19+1 -> 16 | J20: =RANDBETWEEN(120,420) -> 273 | K20: =IF(J20>=$D$18,$D$18,J20) -> 270 | L20: =$D$18-K20 -> 0 | M20: =K20*5 -> 1350 | N20: =-$D$10 -> -20 | O20: =-$D$6*$D$18 -> -810 | P20: =-L20*$D$9 -> 0 | Q20: =L20*($D$6*$D$8) -> 0 | R20: =SUM(M20:Q20) -> 520 | S20: =IF(R20<0,1,0) -> 0
I21: =I20+1 -> 17 | J21: =RANDBETWEEN(120,420) -> 329 | K21: =IF(J21>=$D$18,$D$18,J21) -> 270 | L21: =$D$18-K21 -> 0 | M21: =K21*5 -> 1350 | N21: =-$D$10 -> -20 | O21: =-$D$6*$D$18 -> -810 | P21: =-L21*$D$9 -> 0 | Q21: =L21*($D$6*$D$8) -> 0 | R21: =SUM(M21:Q21) -> 520 | S21: =IF(R21<0,1,0) -> 0
I22: =I21+1 -> 18 | J22: =RANDBETWEEN(120,420) -> 256 | K22: =IF(J22>=$D$18,$D$18,J22) -> 256 | L22: =$D$18-K22 -> 14 | M22: =K22*5 -> 1280 | N22: =-$D$10 -> -20 | O22: =-$D$6*$D$18 -> -810 | P22: =-L22*$D$9 -> -7 | Q22: =L22*($D$6*$D$8) -> 21 | R22: =SUM(M22:Q22) -> 464 | S22: =IF(R22<0,1,0) -> 0
I23: =I22+1 -> 19 | J23: =RANDBETWEEN(120,420) -> 175 | K23: =IF(J23>=$D$18,$D$18,J23) -> 175 | L23: =$D$18-K23 -> 95 | M23: =K23*5 -> 875 | N23: =-$D$10 -> -20 | O23: =-$D$6*$D$18 -> -810 | P23: =-L23*$D$9 -> -47.5 | Q23: =L23*($D$6*$D$8) -> 142.5 | R23: =SUM(M23:Q23) -> 140 | S23: =IF(R23<0,1,0) -> 0
I24: =I23+1 -> 20 | J24: =RANDBETWEEN(120,420) -> 261 | K24: =IF(J24>=$D$18,$D$18,J24) -> 261 | L24: =$D$18-K24 -> 9 | M24: =K24*5 -> 1305 | N24: =-$D$10 -> -20 | O24: =-$D$6*$D$18 -> -810 | P24: =-L24*$D$9 -> -4.5 | Q24: =L24*($D$6*$D$8) -> 13.5 | R24: =SUM(M24:Q24) -> 484 | S24: =IF(R24<0,1,0) -> 0
I25: =I24+1 -> 21 | J25: =RANDBETWEEN(120,420) -> 143 | K25: =IF(J25>=$D$18,$D$18,J25) -> 143 | L25: =$D$18-K25 -> 127 | M25: =K25*5 -> 715 | N25: =-$D$10 -> -20 | O25: =-$D$6*$D$18 -> -810 | P25: =-L25*$D$9 -> -63.5 | Q25: =L25*($D$6*$D$8) -> 190.5 | R25: =SUM(M25:Q25) -> 12 | S25: =IF(R25<0,1,0) -> 0
I26: =I25+1 -> 22 | J26: =RANDBETWEEN(120,420) -> 185 | K26: =IF(J26>=$D$18,$D$18,J26) -> 185 | L26: =$D$18-K26 -> 85 | M26: =K26*5 -> 925 | N26: =-$D$10 -> -20 | O26: =-$D$6*$D$18 -> -810 | P26: =-L26*$D$9 -> -42.5 | Q26: =L26*($D$6*$D$8) -> 127.5 | R26: =SUM(M26:Q26) -> 180 | S26: =IF(R26<0,1,0) -> 0
I27: =I26+1 -> 23 | J27: =RANDBETWEEN(120,420) -> 180 | K27: =IF(J27>=$D$18,$D$18,J27) -> 180 | L27: =$D$18-K27 -> 90 | M27: =K27*5 -> 900 | N27: =-$D$10 -> -20 | O27: =-$D$6*$D$18 -> -810 | P27: =-L27*$D$9 -> -45 | Q27: =L27*($D$6*$D$8) -> 135 | R27: =SUM(M27:Q27) -> 160 | S27: =IF(R27<0,1,0) -> 0
I28: =I27+1 -> 24 | J28: =RANDBETWEEN(120,420) -> 314 | K28: =IF(J28>=$D$18,$D$18,J28) -> 270 | L28: =$D$18-K28 -> 0 | M28: =K28*5 -> 1350 | N28: =-$D$10 -> -20 | O28: =-$D$6*$D$18 -> -810 | P28: =-L28*$D$9 -> 0 | Q28: =L28*($D$6*$D$8) -> 0 | R28: =SUM(M28:Q28) -> 520 | S28: =IF(R28<0,1,0) -> 0
I29: =I28+1 -> 25 | J29: =RANDBETWEEN(120,420) -> 397 | K29: =IF(J29>=$D$18,$D$18,J29) -> 270 | L29: =$D$18-K29 -> 0 | M29: =K29*5 -> 1350 | N29: =-$D$10 -> -20 | O29: =-$D$6*$D$18 -> -810 | P29: =-L29*$D$9 -> 0 | Q29: =L29*($D$6*$D$8) -> 0 | R29: =SUM(M29:Q29) -> 520 | S29: =IF(R29<0,1,0) -> 0
I30: =I29+1 -> 26 | J30: =RANDBETWEEN(120,420) -> 271 | K30: =IF(J30>=$D$18,$D$18,J30) -> 270 | L30: =$D$18-K30 -> 0 | M30: =K30*5 -> 1350 | N30: =-$D$10 -> -20 | O30: =-$D$6*$D$18 -> -810 | P30: =-L30*$D$9 -> 0 | Q30: =L30*($D$6*$D$8) -> 0 | R30: =SUM(M30:Q30) -> 520 | S30: =IF(R30<0,1,0) -> 0
... I504: =I503+1 -> 500 | J504: =RANDBETWEEN(120,420) -> 325 | K504: =IF(J504>=$D$18,$D$18,J504) -> 270 | L504: =$D$18-K504 -> 0 | M504: =K504*5 -> 1350 | N504: =-$D$10 -> -20 | O504: =-$D$6*$D$18 -> -810 | P504: =-L504*$D$9 -> 0 | Q504: =L504*($D$6*$D$8) -> 0 | R504: =SUM(M504:Q504) -> 520 | S504: =IF(R504<0,1,0) -> 0
J505: =AVERAGE(J5:J504) -> 272.436 | Q505: Avg Profit[500 simulation] | R505: =AVERAGE(R5:R504) -> 374.336
Q506: E[Profit] | R506: ='4'!N33 -> 370
Q507: Std Dev of Profit | R507: =STDEV(R5:R504) -> 193.57284
Q508: No. of instance of loss | R508: =SUM(S5:S504) -> 33
Q509: P(loss)= | R509: =R508/500 -> 0.066

Sheet Sheet2
J19: 94.2 | K19: 0.15 | L19: =K19*J19 -> 14.13
J20: =39.5/40*100 -> 98.75 | K20: 0.1 | L20: =K20*J20 -> 9.875
J21: 84.5 | K21: 0.5 | L21: =K21*J21 -> 42.25
J22: 100 | K22: 0.25 | L22: =K22*J22 -> 25
L23: =SUM(L19:L22) -> 91.255

Sheet 6
N3: Leisure Limited awards $40,000 to the stand with highest sales. SparkFire estimates a
B4: a) | C4: From 1,2,3 we have below X* at various Selling prices and fraction as refund | N4: 5% chance of winning if actual sales are ≥400 units. Other states use 3% if actual sales
E5: X* at various fractions of refund | N5: ≥380 or 7% if actual sales ≥420 are mentioned as context.
E6: 0.25 | F6: 0.5 | G6: 0.75 | N6: (a) Modify your profit model to account for the possibility of awards.
C7: Sellling Price | D7: 5 | E7: ='3'!D19 -> 246.31579 | F7: ='1and2'!C23 -> 270 | G7: ='3'!F19 -> 304.61538 | N7: (b) Find the new quantity Q∗∗ that maximizes total expected returns.
D8: 6 | E8: ='3'!D25 -> 276.52174 | F8: ='1and2'!C40 -> 300 | G8: ='3'!F25 -> 331.76471 | N8: (c) Compare Q∗∗ to Q∗ (from Part 2) and discuss how this incentive scheme encourages
N9: risk-seeking or risk-averse behavior.
C10: Now below are the changes of winning
D12: Sales | E12: Probability of winning | G12: Correspond X*
D13: >=400 | E13: 0.05 | G13: Nil
D14: >=380 | E14: 0.03 | G14: Nil
D15: >=420 | E15: 0.07 | G15: Nil
C17: Lets find X* with below add ons
C18: 1. Assuming sales >=400, then Addional revenue=40000*.05= | H18: =40000*0.05 -> 2000 | I18: overall; So per unit on 400 (minimum qty)= | M18: =2000/400 -> 5 | N18: $per unit
C19: So Cu=5+5-3= | E19: =2+5 -> 7
C20: Co=3-0.5*3+.5= | E20: =3-0.5*3+0.5 -> 2
C21: So F(X*)= | E21: =E19/(E20+E19) -> 0.77777778
C22: X*= | E22: =E21*(420-120)+120 -> 353.33333 | G22: at 0.5 refund fraction
C24: 1. Assuming X* >=380, then Addional revenue=40000*.03= | H24: =40000*0.03 -> 1200 | I24: overall; So per unit on 380 (minimum qty)= | M24: =1200/380 -> 3.1578947 | N24: $per unit
C25: So Cu=5+3.2-3= | E25: =2+3.2 -> 5.2
C26: Co=3-0.5*3+.5= | E26: =3-0.5*3+0.5 -> 2
C27: So F(X*)= | E27: =E25/(E26+E25) -> 0.72222222
C28: X*= | E28: =E27*(420-120)+120 -> 336.66667 | G28: at 0.5 refund fraction
C31: To sell 400 we need atleast 400. suppose we stock 400 units
C32: So demand could be split as either <= 400, or >400 | L32: Probabilities | N32: D< | O32: 380 | P32: =(O32-120)/(420-120) -> 0.86666667 | Q32: 380 | R32: <=D<= | S32: 400 | T32: =(S32-120)/(420-120)-P32 -> 0.066666667 | U32: D< | V32: 400 | W32: =(V32-120)/(420-120) -> 0.93333333 | X32: 400 | Y32: <=D<= | Z32: 420 | AA32: =(Z32-120)/(420-120)-W32 -> 0.066666667 | AB32: <=D | AC32: 420 | AD32: 0
C33: Expected sale when demand<400 is | H33: =(400^2-120^2)/(2*300) -> 242.66667 | L33: Exp Sale | O33: =(O32^2-120^2)/(2*300) -> 216.66667 | V33: =(V32^2-120^2)/(2*300) -> 242.66667 | AC33: =(AC32^2-120^2)/(2*300) -> 270
C34: Expected Profit when Demand<400= | G34: =H33*5+(400-H33)*0.5*3-(400-H33)*0.5-400*3+H36*E14*40000 -> 250.66667 | H34: (without set up cost) | L34: Exp left | O34: =O32-O33 -> 163.33333 | V34: =V32-V33 -> 157.33333 | AC34: =AC32-AC33 -> 150
C35: Probability Demand>=380 but less than 400=P(D<=400)-p(D<=380=(400-120)/(420-120)-(380-120)/(420-120) | L35: Exp profit | O35: =O33*5+O34*0.5*3-O32*3-O34*0.5 -> 106.66667 | V35: =V33*5+V34*0.5*3-V32*3-V34*0.5 -> 170.66667 | AC35: =AC33*5+AC34*0.5*3-AC32*3-AC34*0.5 -> 240
G36: = | H36: =(400-120)/(420-120)-(380-120)/(420-120) -> 0.066666667
C37: Probability Demand>400=1-P(D<=400)= | G37: =1-(400-120)/(420-120) -> 0.066666667 | L37: Sales | M37: Probability of winning
C38: for Demand>400, sale= | E38: 400 | L38: >=400 | M38: 0.05
C39: So profit without winning prize= | F39: =400*5-400*3 -> 800 | G39: for Demand>=400 | L39: >=380 | M39: 0.03
C40: Profit with winning prize= | F40: =800+40000 -> 40800 | L40: >=420 | M40: 0.07
C41: Expected profit when Demand>=400= | G41: =G37*(F39*(1-E13)+F40*E13) -> 186.66667
M43: Qty | N43: Expected Qty | O43: Exp leftover | P43: Reg. exp profit | R43: Profit with reward | S43: Optimal profit w/o reward | V43: Qty | W43: Exp profit | X43: Expected sale | Y43: Exp left over
C44: Total profit= | E44: =G41+G34-20 -> 417.33333 | G44: (inclusive of ordering cost) | M44: =M45-1 -> 372 | N44: =(M44^2-120^2)/(2*300)+M44*(420-M44)/300 -> 266.16 | O44: =M44-N44 -> 105.84 | P44: =N44*5+O44*0.5*3-O44*0.5-M44*3-20 -> 300.64 | R44: =P44 -> 300.64 | S44: =S52 -> 370 | V44: 120 | W44: =X44*5+Y44*0.5*3-Y44*0.5-V44*3-20 -> 220 | X44: =(V44^2-120^2)/(2*300)+V44*(420-V44)/300 -> 120 | Y44: =V44-X44 -> 0
C45: At EOQ in part 2 we saw the profit was= | F45: ='1and2'!J30 -> 370 | G45: which is lesser than with the reward | M45: =M46-1 -> 373 | N45: =(M45^2-120^2)/(2*300)+M45*(420-M45)/300 -> 266.31833 | O45: =M45-N45 -> 106.68167 | P45: =N45*5+O45*0.5*3-O45*0.5-M45*3-20 -> 299.27333 | R45: =P45 -> 299.27333 | S45: =S53 -> 370 | V45: =V44+1 -> 121 | W45: =X45*5+Y45*0.5*3-Y45*0.5-V45*3-20 -> 221.99333 | X45: =(V45^2-120^2)/(2*300)+V45*(420-V45)/300 -> 120.99833 | Y45: =V45-X45 -> 0.0016666667
M46: =M47-1 -> 374 | N46: =(M46^2-120^2)/(2*300)+M46*(420-M46)/300 -> 266.47333 | O46: =M46-N46 -> 107.52667 | P46: =N46*5+O46*0.5*3-O46*0.5-M46*3-20 -> 297.89333 | R46: =P46 -> 297.89333 | S46: =S54 -> 370 | V46: =V45+1 -> 122 | W46: =X46*5+Y46*0.5*3-Y46*0.5-V46*3-20 -> 223.97333 | X46: =(V46^2-120^2)/(2*300)+V46*(420-V46)/300 -> 121.99333 | Y46: =V46-X46 -> 0.0066666667
C47: Now suppose we had inventory at 380 units | M47: =M48-1 -> 375 | N47: =(M47^2-120^2)/(2*300)+M47*(420-M47)/300 -> 266.625 | O47: =M47-N47 -> 108.375 | P47: =N47*5+O47*0.5*3-O47*0.5-M47*3-20 -> 296.5 | R47: =P47 -> 296.5 | S47: =S55 -> 370 | V47: =V46+1 -> 123 | W47: =X47*5+Y47*0.5*3-Y47*0.5-V47*3-20 -> 225.94 | X47: =(V47^2-120^2)/(2*300)+V47*(420-V47)/300 -> 122.985 | Y47: =V47-X47 -> 0.015
C48: Expected sale when demand<380 is | H48: =(380^2-120^2)/(2*300) -> 216.66667 | M48: =M49-1 -> 376 | N48: =(M48^2-120^2)/(2*300)+M48*(420-M48)/300 -> 266.77333 | O48: =M48-N48 -> 109.22667 | P48: =N48*5+O48*0.5*3-O48*0.5-M48*3-20 -> 295.09333 | R48: =P48 -> 295.09333 | S48: =S56 -> 370 | V48: =V47+1 -> 124 | W48: =X48*5+Y48*0.5*3-Y48*0.5-V48*3-20 -> 227.89333 | X48: =(V48^2-120^2)/(2*300)+V48*(420-V48)/300 -> 123.97333 | Y48: =V48-X48 -> 0.026666667
C49: Expected Profit when Demand<380= | G49: =H48*5+(380-H48)*0.5*3-(380-H48)*0.5-380*3 -> 106.66667 | H49: (without set up cost) | M49: =M50-1 -> 377 | N49: =(M49^2-120^2)/(2*300)+M49*(420-M49)/300 -> 266.91833 | O49: =M49-N49 -> 110.08167 | P49: =N49*5+O49*0.5*3-O49*0.5-M49*3-20 -> 293.67333 | R49: =P49 -> 293.67333 | S49: =S57 -> 370 | V49: =V48+1 -> 125 | W49: =X49*5+Y49*0.5*3-Y49*0.5-V49*3-20 -> 229.83333 | X49: =(V49^2-120^2)/(2*300)+V49*(420-V49)/300 -> 124.95833 | Y49: =V49-X49 -> 0.041666667
C50: Probability Demand>=380=1-P(D<=380)=1-(380-120)/(380-120)= | I50: =1-(380-120)/(420-120) -> 0.13333333 | M50: =M51-1 -> 378 | N50: =(M50^2-120^2)/(2*300)+M50*(420-M50)/300 -> 267.06 | O50: =M50-N50 -> 110.94 | P50: =N50*5+O50*0.5*3-O50*0.5-M50*3-20 -> 292.24 | R50: =P50 -> 292.24 | S50: =S58 -> 370 | V50: =V49+1 -> 126 | W50: =X50*5+Y50*0.5*3-Y50*0.5-V50*3-20 -> 231.76 | X50: =(V50^2-120^2)/(2*300)+V50*(420-V50)/300 -> 125.94 | Y50: =V50-X50 -> 0.06
C51: Since we have stock= | E51: 380 | M51: =M52-1 -> 379 | N51: =(M51^2-120^2)/(2*300)+M51*(420-M51)/300 -> 267.19833 | O51: =M51-N51 -> 111.80167 | P51: =N51*5+O51*0.5*3-O51*0.5-M51*3-20 -> 290.79333 | R51: =P51 -> 290.79333 | S51: =S59 -> 370 | V51: =V50+1 -> 127 | W51: =X51*5+Y51*0.5*3-Y51*0.5-V51*3-20 -> 233.67333 | X51: =(V51^2-120^2)/(2*300)+V51*(420-V51)/300 -> 126.91833 | Y51: =V51-X51 -> 0.081666667
C52: So profit without winning prize= | F52: =380*5-380*3 -> 760 | M52: 380 | N52: =(M52^2-120^2)/(2*300)+M52*(420-M52)/300 -> 267.33333 | O52: =M52-N52 -> 112.66667 | P52: =N52*5+O52*0.5*3-O52*0.5-M52*3-20 -> 289.33333 | R52: =P52+40000*0.03*(1-(380-120)/300) -> 449.33333 | S52: ='1and2'!J30 -> 370 | U52: =(380-120)/300 -> 0.86666667 | V52: =V51+1 -> 128 | W52: =X52*5+Y52*0.5*3-Y52*0.5-V52*3-20 -> 235.57333 | X52: =(V52^2-120^2)/(2*300)+V52*(420-V52)/300 -> 127.89333 | Y52: =V52-X52 -> 0.10666667
C53: Profit with winning prize= | F53: =F52+40000 -> 40760 | M53: =M52+1 -> 381 | N53: =(M53^2-120^2)/(2*300)+M53*(420-M53)/300 -> 267.465 | O53: =M53-N53 -> 113.535 | P53: =N53*5+O53*0.5*3-O53*0.5-M53*3-20 -> 287.86 | R53: =P53+40000*0.03*(1-(380-120)/300) -> 447.86 | S53: =S52 -> 370 | U53: =1-U52 -> 0.13333333 | V53: =V52+1 -> 129 | W53: =X53*5+Y53*0.5*3-Y53*0.5-V53*3-20 -> 237.46 | X53: =(V53^2-120^2)/(2*300)+V53*(420-V53)/300 -> 128.865 | Y53: =V53-X53 -> 0.135
C54: Expected profit when Demand>=380= | G54: =I50*(F52*(1-E14)+F53*E14) -> 261.33333 | M54: =M53+1 -> 382 | N54: =(M54^2-120^2)/(2*300)+M54*(420-M54)/300 -> 267.59333 | O54: =M54-N54 -> 114.40667 | P54: =N54*5+O54*0.5*3-O54*0.5-M54*3-20 -> 286.37333 | R54: =P54+40000*0.03*(1-(380-120)/300) -> 446.37333 | S54: =S53 -> 370 | U54: =U53*0.03*40000 -> 160 | V54: =V53+1 -> 130 | W54: =X54*5+Y54*0.5*3-Y54*0.5-V54*3-20 -> 239.33333 | X54: =(V54^2-120^2)/(2*300)+V54*(420-V54)/300 -> 129.83333 | Y54: =V54-X54 -> 0.16666667
C55: Total profit= | E55: =G54+G49-20 -> 348 | G55: (inclusive of ordering cost) | M55: =M54+1 -> 383 | N55: =(M55^2-120^2)/(2*300)+M55*(420-M55)/300 -> 267.71833 | O55: =M55-N55 -> 115.28167 | P55: =N55*5+O55*0.5*3-O55*0.5-M55*3-20 -> 284.87333 | R55: =P55+40000*0.03*(1-(380-120)/300) -> 444.87333 | S55: =S54 -> 370 | V55: =V54+1 -> 131 | W55: =X55*5+Y55*0.5*3-Y55*0.5-V55*3-20 -> 241.19333 | X55: =(V55^2-120^2)/(2*300)+V55*(420-V55)/300 -> 130.79833 | Y55: =V55-X55 -> 0.20166667
C56: At EOQ in part 2 we saw the profit was= | F56: =F45 -> 370 | G56: which is still better | M56: =M55+1 -> 384 | N56: =(M56^2-120^2)/(2*300)+M56*(420-M56)/300 -> 267.84 | O56: =M56-N56 -> 116.16 | P56: =N56*5+O56*0.5*3-O56*0.5-M56*3-20 -> 283.36 | R56: =P56+40000*0.03*(1-(380-120)/300) -> 443.36 | S56: =S55 -> 370 | V56: =V55+1 -> 132 | W56: =X56*5+Y56*0.5*3-Y56*0.5-V56*3-20 -> 243.04 | X56: =(V56^2-120^2)/(2*300)+V56*(420-V56)/300 -> 131.76 | Y56: =V56-X56 -> 0.24
M57: =M56+1 -> 385 | N57: =(M57^2-120^2)/(2*300)+M57*(420-M57)/300 -> 267.95833 | O57: =M57-N57 -> 117.04167 | P57: =N57*5+O57*0.5*3-O57*0.5-M57*3-20 -> 281.83333 | R57: =P57+40000*0.03*(1-(380-120)/300) -> 441.83333 | S57: =S56 -> 370 | V57: =V56+1 -> 133 | W57: =X57*5+Y57*0.5*3-Y57*0.5-V57*3-20 -> 244.87333 | X57: =(V57^2-120^2)/(2*300)+V57*(420-V57)/300 -> 132.71833 | Y57: =V57-X57 -> 0.28166667
C58: Suppose we now hand inventory at 420 units | M58: =M57+1 -> 386 | N58: =(M58^2-120^2)/(2*300)+M58*(420-M58)/300 -> 268.07333 | O58: =M58-N58 -> 117.92667 | P58: =N58*5+O58*0.5*3-O58*0.5-M58*3-20 -> 280.29333 | R58: =P58+40000*0.03*(1-(380-120)/300) -> 440.29333 | S58: =S57 -> 370 | V58: =V57+1 -> 134 | W58: =X58*5+Y58*0.5*3-Y58*0.5-V58*3-20 -> 246.69333 | X58: =(V58^2-120^2)/(2*300)+V58*(420-V58)/300 -> 133.67333 | Y58: =V58-X58 -> 0.32666667
C59: Expected sale now= | E59: =(120+420)/2 -> 270 | M59: =M58+1 -> 387 | N59: =(M59^2-120^2)/(2*300)+M59*(420-M59)/300 -> 268.185 | O59: =M59-N59 -> 118.815 | P59: =N59*5+O59*0.5*3-O59*0.5-M59*3-20 -> 278.74 | R59: =P59+40000*0.03*(1-(380-120)/300) -> 438.74 | S59: =S58 -> 370 | V59: =V58+1 -> 135 | W59: =X59*5+Y59*0.5*3-Y59*0.5-V59*3-20 -> 248.5 | X59: =(V59^2-120^2)/(2*300)+V59*(420-V59)/300 -> 134.625 | Y59: =V59-X59 -> 0.375
C60: Exected profit= | E60: =E59*5+(420-E59)*3*0.5-(420-E59)*0.5-420*3+40000*(E14*H36+E13*G37)-20 -> 433.33333 | G60: (inclusive of ordering cost) | M60: =M59+1 -> 388 | N60: =(M60^2-120^2)/(2*300)+M60*(420-M60)/300 -> 268.29333 | O60: =M60-N60 -> 119.70667 | P60: =N60*5+O60*0.5*3-O60*0.5-M60*3-20 -> 277.17333 | R60: =P60+40000*0.03*(1-(380-120)/300) -> 437.17333 | S60: =S59 -> 370 | V60: =V59+1 -> 136 | W60: =X60*5+Y60*0.5*3-Y60*0.5-V60*3-20 -> 250.29333 | X60: =(V60^2-120^2)/(2*300)+V60*(420-V60)/300 -> 135.57333 | Y60: =V60-X60 -> 0.42666667
M61: =M60+1 -> 389 | N61: =(M61^2-120^2)/(2*300)+M61*(420-M61)/300 -> 268.39833 | O61: =M61-N61 -> 120.60167 | P61: =N61*5+O61*0.5*3-O61*0.5-M61*3-20 -> 275.59333 | R61: =P61+40000*0.03*(1-(380-120)/300) -> 435.59333 | S61: =S60 -> 370 | V61: =V60+1 -> 137 | W61: =X61*5+Y61*0.5*3-Y61*0.5-V61*3-20 -> 252.07333 | X61: =(V61^2-120^2)/(2*300)+V61*(420-V61)/300 -> 136.51833 | Y61: =V61-X61 -> 0.48166667
M62: =M61+1 -> 390 | N62: =(M62^2-120^2)/(2*300)+M62*(420-M62)/300 -> 268.5 | O62: =M62-N62 -> 121.5 | P62: =N62*5+O62*0.5*3-O62*0.5-M62*3-20 -> 274 | R62: =P62+40000*0.03*(1-(380-120)/300) -> 434 | S62: =S61 -> 370 | V62: =V61+1 -> 138 | W62: =X62*5+Y62*0.5*3-Y62*0.5-V62*3-20 -> 253.84 | X62: =(V62^2-120^2)/(2*300)+V62*(420-V62)/300 -> 137.46 | Y62: =V62-X62 -> 0.54
C63: Final table | M63: =M62+1 -> 391 | N63: =(M63^2-120^2)/(2*300)+M63*(420-M63)/300 -> 268.59833 | O63: =M63-N63 -> 122.40167 | P63: =N63*5+O63*0.5*3-O63*0.5-M63*3-20 -> 272.39333 | R63: =P63+40000*0.03*(1-(380-120)/300) -> 432.39333 | S63: =S62 -> 370 | V63: =V62+1 -> 139 | W63: =X63*5+Y63*0.5*3-Y63*0.5-V63*3-20 -> 255.59333 | X63: =(V63^2-120^2)/(2*300)+V63*(420-V63)/300 -> 138.39833 | Y63: =V63-X63 -> 0.60166667
C64: Without reward | E64: With reward | M64: =M63+1 -> 392 | N64: =(M64^2-120^2)/(2*300)+M64*(420-M64)/300 -> 268.69333 | O64: =M64-N64 -> 123.30667 | P64: =N64*5+O64*0.5*3-O64*0.5-M64*3-20 -> 270.77333 | R64: =P64+40000*0.03*(1-(380-120)/300) -> 430.77333 | S64: =S63 -> 370 | V64: =V63+1 -> 140 | W64: =X64*5+Y64*0.5*3-Y64*0.5-V64*3-20 -> 257.33333 | X64: =(V64^2-120^2)/(2*300)+V64*(420-V64)/300 -> 139.33333 | Y64: =V64-X64 -> 0.66666667
B65: Optimal Q | C65: ='1and2'!C23 -> 270 | D65: 380 | E65: 400 | F65: 420 | M65: =M64+1 -> 393 | N65: =(M65^2-120^2)/(2*300)+M65*(420-M65)/300 -> 268.785 | O65: =M65-N65 -> 124.215 | P65: =N65*5+O65*0.5*3-O65*0.5-M65*3-20 -> 269.14 | R65: =P65+40000*0.03*(1-(380-120)/300) -> 429.14 | S65: =S64 -> 370 | V65: =V64+1 -> 141 | W65: =X65*5+Y65*0.5*3-Y65*0.5-V65*3-20 -> 259.06 | X65: =(V65^2-120^2)/(2*300)+V65*(420-V65)/300 -> 140.265 | Y65: =V65-X65 -> 0.735
B66: Profit | C66: ='1and2'!J30 -> 370 | D66: =E55 -> 348 | E66: =E44 -> 417.33333 | F66: =E60 -> 433.33333 | M66: =M65+1 -> 394 | N66: =(M66^2-120^2)/(2*300)+M66*(420-M66)/300 -> 268.87333 | O66: =M66-N66 -> 125.12667 | P66: =N66*5+O66*0.5*3-O66*0.5-M66*3-20 -> 267.49333 | R66: =P66+40000*0.03*(1-(380-120)/300) -> 427.49333 | S66: =S65 -> 370 | V66: =V65+1 -> 142 | W66: =X66*5+Y66*0.5*3-Y66*0.5-V66*3-20 -> 260.77333 | X66: =(V66^2-120^2)/(2*300)+V66*(420-V66)/300 -> 141.19333 | Y66: =V66-X66 -> 0.80666667
M67: =M66+1 -> 395 | N67: =(M67^2-120^2)/(2*300)+M67*(420-M67)/300 -> 268.95833 | O67: =M67-N67 -> 126.04167 | P67: =N67*5+O67*0.5*3-O67*0.5-M67*3-20 -> 265.83333 | R67: =P67+40000*0.03*(1-(380-120)/300) -> 425.83333 | S67: =S66 -> 370 | V67: =V66+1 -> 143 | W67: =X67*5+Y67*0.5*3-Y67*0.5-V67*3-20 -> 262.47333 | X67: =(V67^2-120^2)/(2*300)+V67*(420-V67)/300 -> 142.11833 | Y67: =V67-X67 -> 0.88166667
M68: =M67+1 -> 396 | N68: =(M68^2-120^2)/(2*300)+M68*(420-M68)/300 -> 269.04 | O68: =M68-N68 -> 126.96 | P68: =N68*5+O68*0.5*3-O68*0.5-M68*3-20 -> 264.16 | R68: =P68+40000*0.03*(1-(380-120)/300) -> 424.16 | S68: =S67 -> 370 | V68: =V67+1 -> 144 | W68: =X68*5+Y68*0.5*3-Y68*0.5-V68*3-20 -> 264.16 | X68: =(V68^2-120^2)/(2*300)+V68*(420-V68)/300 -> 143.04 | Y68: =V68-X68 -> 0.96
M69: =M68+1 -> 397 | N69: =(M69^2-120^2)/(2*300)+M69*(420-M69)/300 -> 269.11833 | O69: =M69-N69 -> 127.88167 | P69: =N69*5+O69*0.5*3-O69*0.5-M69*3-20 -> 262.47333 | R69: =P69+40000*0.03*(1-(380-120)/300) -> 422.47333 | S69: =S68 -> 370 | V69: =V68+1 -> 145 | W69: =X69*5+Y69*0.5*3-Y69*0.5-V69*3-20 -> 265.83333 | X69: =(V69^2-120^2)/(2*300)+V69*(420-V69)/300 -> 143.95833 | Y69: =V69-X69 -> 1.0416667
M70: =M69+1 -> 398 | N70: =(M70^2-120^2)/(2*300)+M70*(420-M70)/300 -> 269.19333 | O70: =M70-N70 -> 128.80667 | P70: =N70*5+O70*0.5*3-O70*0.5-M70*3-20 -> 260.77333 | R70: =P70+40000*0.03*(1-(380-120)/300) -> 420.77333 | S70: =S69 -> 370 | V70: =V69+1 -> 146 | W70: =X70*5+Y70*0.5*3-Y70*0.5-V70*3-20 -> 267.49333 | X70: =(V70^2-120^2)/(2*300)+V70*(420-V70)/300 -> 144.87333 | Y70: =V70-X70 -> 1.1266667
M71: =M70+1 -> 399 | N71: =(M71^2-120^2)/(2*300)+M71*(420-M71)/300 -> 269.265 | O71: =M71-N71 -> 129.735 | P71: =N71*5+O71*0.5*3-O71*0.5-M71*3-20 -> 259.06 | R71: =P71+40000*0.03*(1-(380-120)/300) -> 419.06 | S71: =S70 -> 370 | V71: =V70+1 -> 147 | W71: =X71*5+Y71*0.5*3-Y71*0.5-V71*3-20 -> 269.14 | X71: =(V71^2-120^2)/(2*300)+V71*(420-V71)/300 -> 145.785 | Y71: =V71-X71 -> 1.215
M72: =M71+1 -> 400 | N72: =(M72^2-120^2)/(2*300)+M72*(420-M72)/300 -> 269.33333 | O72: =M72-N72 -> 130.66667 | P72: =N72*5+O72*0.5*3-O72*0.5-M72*3-20 -> 257.33333 | R72: =P72+40000*0.05*(1-(400-120)/300)+40000*0.03*((400-120)/300-(380-120)/300) -> 470.66667 | S72: =S71 -> 370 | V72: =V71+1 -> 148 | W72: =X72*5+Y72*0.5*3-Y72*0.5-V72*3-20 -> 270.77333 | X72: =(V72^2-120^2)/(2*300)+V72*(420-V72)/300 -> 146.69333 | Y72: =V72-X72 -> 1.3066667
M73: =M72+1 -> 401 | N73: =(M73^2-120^2)/(2*300)+M73*(420-M73)/300 -> 269.39833 | O73: =M73-N73 -> 131.60167 | P73: =N73*5+O73*0.5*3-O73*0.5-M73*3-20 -> 255.59333 | R73: =P73+40000*0.05*(1-(400-120)/300)+40000*0.03*((400-120)/300-(380-120)/300) -> 468.92667 | S73: =S72 -> 370 | V73: =V72+1 -> 149 | W73: =X73*5+Y73*0.5*3-Y73*0.5-V73*3-20 -> 272.39333 | X73: =(V73^2-120^2)/(2*300)+V73*(420-V73)/300 -> 147.59833 | Y73: =V73-X73 -> 1.4016667
M74: =M73+1 -> 402 | N74: =(M74^2-120^2)/(2*300)+M74*(420-M74)/300 -> 269.46 | O74: =M74-N74 -> 132.54 | P74: =N74*5+O74*0.5*3-O74*0.5-M74*3-20 -> 253.84 | R74: =P74+40000*0.05*(1-(400-120)/300)+40000*0.03*((400-120)/300-(380-120)/300) -> 467.17333 | S74: =S73 -> 370 | V74: =V73+1 -> 150 | W74: =X74*5+Y74*0.5*3-Y74*0.5-V74*3-20 -> 274 | X74: =(V74^2-120^2)/(2*300)+V74*(420-V74)/300 -> 148.5 | Y74: =V74-X74 -> 1.5
M75: =M74+1 -> 403 | N75: =(M75^2-120^2)/(2*300)+M75*(420-M75)/300 -> 269.51833 | O75: =M75-N75 -> 133.48167 | P75: =N75*5+O75*0.5*3-O75*0.5-M75*3-20 -> 252.07333 | R75: =P75+40000*0.05*(1-(400-120)/300)+40000*0.03*((400-120)/300-(380-120)/300) -> 465.40667 | S75: =S74 -> 370 | V75: =V74+1 -> 151 | W75: =X75*5+Y75*0.5*3-Y75*0.5-V75*3-20 -> 275.59333 | X75: =(V75^2-120^2)/(2*300)+V75*(420-V75)/300 -> 149.39833 | Y75: =V75-X75 -> 1.6016667
M76: =M75+1 -> 404 | N76: =(M76^2-120^2)/(2*300)+M76*(420-M76)/300 -> 269.57333 | O76: =M76-N76 -> 134.42667 | P76: =N76*5+O76*0.5*3-O76*0.5-M76*3-20 -> 250.29333 | R76: =P76+40000*0.05*(1-(400-120)/300)+40000*0.03*((400-120)/300-(380-120)/300) -> 463.62667 | S76: =S75 -> 370 | V76: =V75+1 -> 152 | W76: =X76*5+Y76*0.5*3-Y76*0.5-V76*3-20 -> 277.17333 | X76: =(V76^2-120^2)/(2*300)+V76*(420-V76)/300 -> 150.29333 | Y76: =V76-X76 -> 1.7066667
M77: =M76+1 -> 405 | N77: =(M77^2-120^2)/(2*300)+M77*(420-M77)/300 -> 269.625 | O77: =M77-N77 -> 135.375 | P77: =N77*5+O77*0.5*3-O77*0.5-M77*3-20 -> 248.5 | R77: =P77+40000*0.05*(1-(400-120)/300)+40000*0.03*((400-120)/300-(380-120)/300) -> 461.83333 | S77: =S76 -> 370 | V77: =V76+1 -> 153 | W77: =X77*5+Y77*0.5*3-Y77*0.5-V77*3-20 -> 278.74 | X77: =(V77^2-120^2)/(2*300)+V77*(420-V77)/300 -> 151.185 | Y77: =V77-X77 -> 1.815
M78: =M77+1 -> 406 | N78: =(M78^2-120^2)/(2*300)+M78*(420-M78)/300 -> 269.67333 | O78: =M78-N78 -> 136.32667 | P78: =N78*5+O78*0.5*3-O78*0.5-M78*3-20 -> 246.69333 | R78: =P78+40000*0.05*(1-(400-120)/300)+40000*0.03*((400-120)/300-(380-120)/300) -> 460.02667 | S78: =S77 -> 370 | V78: =V77+1 -> 154 | W78: =X78*5+Y78*0.5*3-Y78*0.5-V78*3-20 -> 280.29333 | X78: =(V78^2-120^2)/(2*300)+V78*(420-V78)/300 -> 152.07333 | Y78: =V78-X78 -> 1.9266667
M79: =M78+1 -> 407 | N79: =(M79^2-120^2)/(2*300)+M79*(420-M79)/300 -> 269.71833 | O79: =M79-N79 -> 137.28167 | P79: =N79*5+O79*0.5*3-O79*0.5-M79*3-20 -> 244.87333 | R79: =P79+40000*0.05*(1-(400-120)/300)+40000*0.03*((400-120)/300-(380-120)/300) -> 458.20667 | S79: =S78 -> 370 | V79: =V78+1 -> 155 | W79: =X79*5+Y79*0.5*3-Y79*0.5-V79*3-20 -> 281.83333 | X79: =(V79^2-120^2)/(2*300)+V79*(420-V79)/300 -> 152.95833 | Y79: =V79-X79 -> 2.0416667
M80: =M79+1 -> 408 | N80: =(M80^2-120^2)/(2*300)+M80*(420-M80)/300 -> 269.76 | O80: =M80-N80 -> 138.24 | P80: =N80*5+O80*0.5*3-O80*0.5-M80*3-20 -> 243.04 | R80: =P80+40000*0.05*(1-(400-120)/300)+40000*0.03*((400-120)/300-(380-120)/300) -> 456.37333 | S80: =S79 -> 370 | V80: =V79+1 -> 156 | W80: =X80*5+Y80*0.5*3-Y80*0.5-V80*3-20 -> 283.36 | X80: =(V80^2-120^2)/(2*300)+V80*(420-V80)/300 -> 153.84 | Y80: =V80-X80 -> 2.16
M81: =M80+1 -> 409 | N81: =(M81^2-120^2)/(2*300)+M81*(420-M81)/300 -> 269.79833 | O81: =M81-N81 -> 139.20167 | P81: =N81*5+O81*0.5*3-O81*0.5-M81*3-20 -> 241.19333 | R81: =P81+40000*0.05*(1-(400-120)/300)+40000*0.03*((400-120)/300-(380-120)/300) -> 454.52667 | S81: =S80 -> 370 | V81: =V80+1 -> 157 | W81: =X81*5+Y81*0.5*3-Y81*0.5-V81*3-20 -> 284.87333 | X81: =(V81^2-120^2)/(2*300)+V81*(420-V81)/300 -> 154.71833 | Y81: =V81-X81 -> 2.2816667
M82: =M81+1 -> 410 | N82: =(M82^2-120^2)/(2*300)+M82*(420-M82)/300 -> 269.83333 | O82: =M82-N82 -> 140.16667 | P82: =N82*5+O82*0.5*3-O82*0.5-M82*3-20 -> 239.33333 | R82: =P82+40000*0.05*(1-(400-120)/300)+40000*0.03*((400-120)/300-(380-120)/300) -> 452.66667 | S82: =S81 -> 370 | V82: =V81+1 -> 158 | W82: =X82*5+Y82*0.5*3-Y82*0.5-V82*3-20 -> 286.37333 | X82: =(V82^2-120^2)/(2*300)+V82*(420-V82)/300 -> 155.59333 | Y82: =V82-X82 -> 2.4066667
M83: =M82+1 -> 411 | N83: =(M83^2-120^2)/(2*300)+M83*(420-M83)/300 -> 269.865 | O83: =M83-N83 -> 141.135 | P83: =N83*5+O83*0.5*3-O83*0.5-M83*3-20 -> 237.46 | R83: =P83+40000*0.05*(1-(400-120)/300)+40000*0.03*((400-120)/300-(380-120)/300) -> 450.79333 | S83: =S82 -> 370 | V83: =V82+1 -> 159 | W83: =X83*5+Y83*0.5*3-Y83*0.5-V83*3-20 -> 287.86 | X83: =(V83^2-120^2)/(2*300)+V83*(420-V83)/300 -> 156.465 | Y83: =V83-X83 -> 2.535
... M91: =M90+1 -> 419 | N91: =(M91^2-120^2)/(2*300)+M91*(420-M91)/300 -> 269.99833 | O91: =M91-N91 -> 149.00167 | P91: =N91*5+O91*0.5*3-O91*0.5-M91*3-20 -> 221.99333 | R91: =P91+40000*0.05*(1-(400-120)/300)+40000*0.03*((400-120)/300-(380-120)/300) -> 435.32667 | S91: =S90 -> 370 | V91: =V90+1 -> 167 | W91: =X91*5+Y91*0.5*3-Y91*0.5-V91*3-20 -> 299.27333 | X91: =(V91^2-120^2)/(2*300)+V91*(420-V91)/300 -> 163.31833 | Y91: =V91-X91 -> 3.6816667
M92: =M91+1 -> 420 | N92: =(M92^2-120^2)/(2*300)+M92*(420-M92)/300 -> 270 | O92: =M92-N92 -> 150 | P92: =N92*5+O92*0.5*3-O92*0.5-M92*3-20 -> 220 | R92: =(M92^2-120^2)/(2*300)*5+(M92-(M92^2-120^2)/(2*300))*3*0.5-M92*3-(M92-(M92^2-120^2)/(2*300))*0.5+40000*(1-(400-120)/(420-120))*0.05+M92*(1-(M92-120)/(420-120))*2-20+40000*$T$32*0.03 -> 433.33333 | S92: =S91 -> 370 | V92: =V91+1 -> 168 | W92: =X92*5+Y92*0.5*3-Y92*0.5-V92*3-20 -> 300.64 | X92: =(V92^2-120^2)/(2*300)+V92*(420-V92)/300 -> 164.16 | Y92: =V92-X92 -> 3.84
V93: =V92+1 -> 169 | W93: =X93*5+Y93*0.5*3-Y93*0.5-V93*3-20 -> 301.99333 | X93: =(V93^2-120^2)/(2*300)+V93*(420-V93)/300 -> 164.99833 | Y93: =V93-X93 -> 4.0016667
V94: =V93+1 -> 170 | W94: =X94*5+Y94*0.5*3-Y94*0.5-V94*3-20 -> 303.33333 | X94: =(V94^2-120^2)/(2*300)+V94*(420-V94)/300 -> 165.83333 | Y94: =V94-X94 -> 4.1666667
V95: =V94+1 -> 171 | W95: =X95*5+Y95*0.5*3-Y95*0.5-V95*3-20 -> 304.66 | X95: =(V95^2-120^2)/(2*300)+V95*(420-V95)/300 -> 166.665 | Y95: =V95-X95 -> 4.335
V96: =V95+1 -> 172 | W96: =X96*5+Y96*0.5*3-Y96*0.5-V96*3-20 -> 305.97333 | X96: =(V96^2-120^2)/(2*300)+V96*(420-V96)/300 -> 167.49333 | Y96: =V96-X96 -> 4.5066667
V97: =V96+1 -> 173 | W97: =X97*5+Y97*0.5*3-Y97*0.5-V97*3-20 -> 307.27333 | X97: =(V97^2-120^2)/(2*300)+V97*(420-V97)/300 -> 168.31833 | Y97: =V97-X97 -> 4.6816667
V98: =V97+1 -> 174 | W98: =X98*5+Y98*0.5*3-Y98*0.5-V98*3-20 -> 308.56 | X98: =(V98^2-120^2)/(2*300)+V98*(420-V98)/300 -> 169.14 | Y98: =V98-X98 -> 4.86
V99: =V98+1 -> 175 | W99: =X99*5+Y99*0.5*3-Y99*0.5-V99*3-20 -> 309.83333 | X99: =(V99^2-120^2)/(2*300)+V99*(420-V99)/300 -> 169.95833 | Y99: =V99-X99 -> 5.0416667
V100: =V99+1 -> 176 | W100: =X100*5+Y100*0.5*3-Y100*0.5-V100*3-20 -> 311.09333 | X100: =(V100^2-120^2)/(2*300)+V100*(420-V100)/300 -> 170.77333 | Y100: =V100-X100 -> 5.2266667
V101: =V100+1 -> 177 | W101: =X101*5+Y101*0.5*3-Y101*0.5-V101*3-20 -> 312.34 | X101: =(V101^2-120^2)/(2*300)+V101*(420-V101)/300 -> 171.585 | Y101: =V101-X101 -> 5.415
V102: =V101+1 -> 178 | W102: =X102*5+Y102*0.5*3-Y102*0.5-V102*3-20 -> 313.57333 | X102: =(V102^2-120^2)/(2*300)+V102*(420-V102)/300 -> 172.39333 | Y102: =V102-X102 -> 5.6066667
V103: =V102+1 -> 179 | W103: =X103*5+Y103*0.5*3-Y103*0.5-V103*3-20 -> 314.79333 | X103: =(V103^2-120^2)/(2*300)+V103*(420-V103)/300 -> 173.19833 | Y103: =V103-X103 -> 5.8016667
V104: =V103+1 -> 180 | W104: =X104*5+Y104*0.5*3-Y104*0.5-V104*3-20 -> 316 | X104: =(V104^2-120^2)/(2*300)+V104*(420-V104)/300 -> 174 | Y104: =V104-X104 -> 6
... V344: =V343+1 -> 420 | W344: =X344*5+Y344*0.5*3-Y344*0.5-V344*3-20 -> 220 | X344: =(V344^2-120^2)/(2*300)+V344*(420-V344)/300 -> 270 | Y344: =V344-X344 -> 150

Sheet 7
E4: Optimal qty at unit cost | T4: Expected left over | U4: Salvage value | V4: Shipping cost | W4: Net Profit
B5: Order Qty | C5: Unit cost | E5: (@ $5 selling price) | G5: (@ $6 selling price) | I5: Comment | L5: Total cost at | M5: Cost Total | N5: Expected Sale qty
B6: 1-199 | C6: 3 | E6: ='1and2'!C23 -> 270 | G6: ='1and2'!C40 -> 300 | I6: Beyond order qty range for that cost | L6: 199 units= | M6: =(199*3+G25)*-1 -> -617 | S6: =(199^2-120^2)/(2*300)+((420-199)*199)/300 -> 188.59833 | T6: =199-S6 -> 10.401667 | U6: =T6*$G$23*C6 -> 15.6025 | V6: =T6*$G$24*-1 -> -5.2008333 | W6: =S6*$G$22+V6+U6+M6 -> 336.39333
B8: 200-399 | C8: 2.85 | E8: =F34 -> 278.28221 | I8: within the range so this should be ordered | L8: =TEXT(E8,"0.00") & " units" -> 278.28 units | M8: =(E8*C8+20)*-1 -> -813.10429 | S8: =(278.28^2-120^2)/(2*300)+((420-278.28)*278.28)/300 -> 236.52574 | T8: =278-S8 -> 41.474264 | U8: =T8*$G$23*C8 -> 59.100826 | V8: =T8*$G$24*-1 -> -20.737132 | W8: =S8*$G$22+V8+U8+M8 -> 407.88808
B10: 400+ | C10: 2.7 | E10: =L34 -> 286.26506 | I10: Below the range of 400 so we use 400 | L10: 400 | M10: =(E10*C10+20)*-1 -> -792.91566 | S10: =(400^2-120^2)/(2*300)+((420-400)*400)/300 -> 269.33333 | T10: =400-S10 -> 130.66667 | U10: =T10*$G$23*C10 -> 176.4 | V10: =T10*$G$24*-1 -> -65.333333 | W10: =S10*$G$22+V10+U10+M10 -> 664.81767
E17: 1 week of sale | K17: 1 week of sale
F18: Uniform dist | G18: 120 | H18: 420 | L18: Uniform dist | M18: 120 | N18: 420
F19: Expected sale= | G19: =AVERAGE(G18:H18) -> 270 | L19: Expected sale= | M19: =AVERAGE(M18:N18) -> 270
F21: Cost=c= | G21: =C8 -> 2.85 | L21: Cost=c= | M21: =C10 -> 2.7
F22: Selling price=p= | G22: 5 | L22: Selling price=p= | M22: 5
F23: Refund fraction= | G23: 0.5 | H23: [0.25-0.75 scenarios] | L23: Refund fraction= | M23: 0.5 | N23: [0.25-0.75 scenarios]
F24: Return shipping= | G24: 0.5 | H24: per unit | L24: Return shipping= | M24: 0.5 | N24: per unit
F25: K= | G25: 20 | H25: per order | L25: K= | M25: 20 | N25: per order
F26: Prize value= | G26: 40000 | L26: Prize value= | M26: 40000
E29: at $5 selling price | K29: at $5 selling price
E30: Co= | F30: 2.85-0.5*2.85+.5= | G30: =G21-0.5*G21+0.5 -> 1.925 | K30: Co= | L30: 2.85-0.5*2.85+.5= | M30: =M21-0.5*M21+0.5 -> 1.85
E31: Cu= | F31: 5-3= | G31: =5-G21 -> 2.15 | K31: Cu= | L31: 5-3= | M31: =5-M21 -> 2.3
E32: F(X*)= | F32: Cu/(Cu+Co)= | G32: =G31/(G31+G30) -> 0.52760736 | K32: F(X*)= | L32: Cu/(Cu+Co)= | M32: =M31/(M31+M30) -> 0.55421687
E34: X*$5,0.5= | F34: =G32*(420-120)+120 -> 278.28221 | K34: X*$5,0.5= | L34: =M32*(420-120)+120 -> 286.26506

Sheet 8
F1: f= | G1: 0.5 | H1: % of cost
F2: Shipping=s= | G2: 0.5
F3: The market signal demands are as follows
H6: Pre Season initial order Q0 cost c0= | I6: 3
H7: In season Expedited top up order Q1(S) cost c1= | I7: 3.6
H8: Per order cost= | I8: 20 | J8: (assuming this for both pre season and In season)
H9: Sale price= | I9: 5 | J9: (assumption)
A10: (a) | E10: Now we order Q0 and then Q1. Let expected Sale be E(S) | I10: . So total Q2=Q0+Q1
D11: Scenarios | G11: E[Revenue] | H11: Cost Var | I11: E[Salvage Val] | J11: E[Shipping cost] | L11: Per order cost | N11: E[Revenue]
G12: a | H12: b | I12: c | J12: d | L12: e | N12: a+c-b-d-e
D13: Dual order | E13: If E(S)≤Q0 | G13: E(S)*5 | H13: [Q0*3+Q1*3.6] | I13: [Q0-E(S)]*3*.5+Q1*3.6*.5 | J13: [Q0+Q1-E(S)]*0.5 | L13: 20*2 | N13: E(S)*5+{[Q0-E(S)]*3*.5+Q1*3.6*.5}-{[Q0*3+Q1*3.6]}-{[Q0+Q1-E(S)]*0.5}-20*2
D14: Dual order | E14: If Q0 ≤E(S)≤ Q. 1 +Q0 | G14: E(S)*5 | H14: [Q0*3+Q1*3.6] | I14: [Q0+Q1-E(S)]*3.6*.5 | J14: [Q0+Q1-E(S)]*0.5 | L14: 20*2 | N14: E(S)*5+{[Q0+Q1-E(S)]*3.6*.5}-{[Q0*3+Q1*3.6]}-{[Q0+Q1-E(S)]*0.5}-20*2
D15: Dual order | E15: if (Q1+Q0 )≤ E(S) | G15: (Q1+Q0 )*5 | H15: [Q0*3+Q1*3.6] | I15: 0 | J15: 0
D16: Single order | E16: If E(S)≤Q 0 | G16: E(S)*5 | H16: Q0*3 | I16: [Q0-E(S)]*3*.5 | J16: [Q0-E(S)]*0.5 | L16: 20 | N16: E(S)*5+{[Q0-E(S)]*3*.5}-Q0*3-{[Q0-E(S)]*0.5}-20
D17: Single order | E17: If E(S)>Q0 | G17: Q0*5 | H17: Q0*3 | I17: 0 | J17: 0 | L17: 20 | N17: Q0*(5-3)-20
A19: (b) | E19: There are two ways to manager this, eigher have just a single pre-season order or have a pre season and then in season order
E20: Lets make the payoff table. The states of nature are D⏐S=High and D⏐S=Low
E21: Decision taken are Ordering optimal quantity basis S=High or S=Low at the beginning with no top up or order S=Low optimal with a top up to match S=High
E22: At pre season cost of $3.00
E23: For D⏐S=High single order
G24: co= 3-0.5*3+.5= | H24: =3-0.5*3+0.5 -> 2
G25: cu=5-3= | H25: =5-3 -> 2
G26: P(D≤Q 0)=cu/(cu+co)= | H26: =H24/(H24+H25) -> 0.5
H27: =H26*(420-240)+240 -> 330
E29: for D⏐S=Low single order
G30: co= 3-0.5*3+.5= | H30: =3-0.5*3+0.5 -> 2
G31: cu=5-3= | H31: =5-3 -> 2
G32: P(D≤Q 0)=cu/(cu+co)= | H32: =H30/(H30+H31) -> 0.5
H33: =H32*(260-120)+120 -> 190 | I33: =190*5-200*3 -> 350
E35: for both pre and in season ordering, the pre order could be placed till Q0/low or Q0/high and then basis high signal, place the next order to add Q1
E36: This looks like a quantity discount problem except the inverse since at higher quantity, the cost is going up. So we can use a similar approach
E37: Lets find Q2/high =Q1+Q0 | H37: (Q0 can be Q0/high or Q0/low)
G38: co= 3.6-0.5*3.6+.5= | H38: =3.6-0.5*3.6+0.5 -> 2.3
G39: cu=5-3.6= | H39: =5-3.6 -> 1.4
G40: P(D≤Q0)=cu/(cu+co)= | H40: =H38/(H38+H39) -> 0.62162162
H41: =H40*(420-240)+240 -> 351.89189
E43: Lets find Q2/low =Q1+Q0
G44: co= 3.6-0.5*3.6+.5= | H44: =3.6-0.5*3.6+0.5 -> 2.3
G45: cu=5-3.6= | H45: =5-3.6 -> 1.4
G46: P(D≤Q0)=cu/(cu+co)= | H46: =H44/(H44+H45) -> 0.62162162
H47: =H46*(260-120)+120 -> 207.02703
D49: (Q0 can be Q0/low only since Q0/high is higher qty than Q2/low)
E50: So pay off table
A52: (c) | D52: Expected Sales and left over | F52: Expected Sales and left over | G52: States of Nature
F53: D⏐High | M53: D⏐low
F54: Exp. sales | K54: Exp. Left over | L54: Exp. sales | R54: Exp. Left over
D55: Single order 352 | J55: =(352^2-240^2)/(2*180)+((420-352)*352)/180 -> 317.15556 | K55: =352-J55 -> 34.844444 | M55: Since Qty ordered is > Max demand | P55: = | Q55: =(120+260)/2 -> 190 | R55: =352-Q55 -> 162
D56: Single order 330 | J56: =(330^2-240^2)/(2*180)+((420-330)*330)/180 -> 307.5 | K56: =330-J56 -> 22.5 | M56: Since Qty ordered is > Max demand | P56: = | Q56: =(120+260)/2 -> 190 | R56: =330-Q56 -> 140
D57: Single order 190 | F57: since min. demand is 240 | I57: = | J57: 190 | K57: 0 | Q57: =(190^2-120^2)/(2*140)+((260-190)*190)/140 -> 172.5 | R57: =190-Q57 -> 17.5
D58: Single order 207 | F58: since min. demand is 240 | I58: = | J58: 207 | K58: 0 | Q58: =(207^2-120^2)/(2*140)+((260-207)*207)/140 -> 179.96786 | R58: =207-Q58 -> 27.032143
D59: dual order 190, (352-190) | J59: =(352^2-240^2)/(2*180)+((420-352)*352)/180 -> 317.15556 | K59: =352-J59 -> 34.844444 | M59: Since Qty ordered is > Max demand | P59: = | Q59: =(120+260)/2 -> 190 | R59: =352-Q59 -> 162
D60: Dual order 190, (330-190) | J60: =(330^2-240^2)/(2*180)+((420-330)*330)/180 -> 307.5 | K60: =330-J60 -> 22.5 | M60: Since Qty ordered is > Max demand | P60: = | Q60: =(120+260)/2 -> 190 | R60: =330-Q60 -> 140
D61: Dual order 190, (207-190) | F61: since min. demand is 240 | I61: = | J61: 207 | K61: 0 | Q61: =(207^2-120^2)/(2*140)+((260-207)*207)/140 -> 179.96786 | R61: =207-Q61 -> 27.032143
D62: Dual order 207, (352-207) | J62: =(352^2-240^2)/(2*180)+((420-352)*352)/180 -> 317.15556 | K62: =352-J62 -> 34.844444 | M62: Since Qty ordered is > Max demand | P62: = | Q62: =(120+260)/2 -> 190 | R62: =352-Q62 -> 162
D63: Dual order 207, (330-207) | J63: =(330^2-240^2)/(2*180)+((420-330)*330)/180 -> 307.5 | K63: =330-J63 -> 22.5 | M63: Since Qty ordered is > Max demand | P63: = | Q63: =(120+260)/2 -> 190 | R63: =330-Q63 -> 140
D64: Dual order 330,(352-330) | J64: =(352^2-240^2)/(2*180)+((420-352)*352)/180 -> 317.15556 | K64: =352-J64 -> 34.844444 | M64: Since Qty ordered is > Max demand | P64: = | Q64: =(120+260)/2 -> 190 | R64: =352-Q64 -> 162
D67: Expected Profit
G69: D⏐High | I69: =M53 -> D⏐low | K69: E(Profit) | M69: E(Profit) | N69: E(Profit) | O69: E(Profit) | P69: E(Profit) | Q69: E(Profit) | R69: E(Profit) | S69: E(Profit) | T69: E(Profit) | U69: E(Profit)
D70: Single order 352 | G70: =J55*5+K55*3*0.5-K55*0.5-352*3-20 -> 544.62222 | I70: =Q55*5+R55*3*0.5-R55*0.5-352*3-20 -> 36 | K70: =G70*$G$80+I70*$I$80 -> 331.00089 | M70: 188.58667 | N70: 239.44889 | O70: 214.01778 | P70: 264.88 | Q70: 290.31111 | R70: 341.17333 | S70: 392.03556 | T70: 442.89778 | U70: 493.76
D71: Single order 330 | G71: =J56*5+K56*3*0.5-K56*0.5-330*3-20 -> 550 | I71: =Q56*5+R56*3*0.5-R56*0.5-330*3-20 -> 80 | K71: =G71*$G$80+I71*$I$80 -> 352.6 | M71: 221 | N71: 268 | O71: 244.5 | P71: 291.5 | Q71: 315 | R71: 362 | S71: 409 | T71: 456 | U71: 503
D72: Single order 190 | G72: =J57*5+K57*3*0.5-K57*0.5-190*3-20 -> 360 | I72: =Q57*5+R57*3*0.5-R57*0.5-190*3-20 -> 290 | K72: =G72*$G$80+I72*$I$80 -> 330.6 | M72: 311 | N72: 318 | O72: 314.5 | P72: 321.5 | Q72: 325 | R72: 332 | S72: 339 | T72: 346 | U72: 353
D73: Single order 207 | G73: =J58*5+K58*3*0.5-K58*0.5-207*3-20 -> 394 | I73: =Q58*5+R58*3*0.5-R58*0.5-207*3-20 -> 285.87143 | K73: =G73*$G$80+I73*$I$80 -> 348.586 | M73: 318.31 | N73: 329.12286 | O73: 323.71643 | P73: 334.52929 | Q73: 339.93571 | R73: 350.74857 | S73: 361.56143 | T73: 372.37429 | U73: 383.18714
D74: dual order 190, (352-190) | G74: =J59*5+K59*3.6*0.5-K59*0.5-190*3-(352-190)*3.6-20*2 -> 437.87556 | I74: =Q59*5+R59*3*0.5-R59*0.5-190*3-(352-190)*3.6-20*2 -> -81.2 | K74: =G74*$G$80+I74*$I$80 -> 219.86382 | M74: 74.522667 | N74: 126.43022 | O74: 100.47644 | P74: 152.384 | Q74: 178.33778 | R74: 230.24533 | S74: 282.15289 | T74: 334.06044 | U74: 385.968
D75: Dual order 190, (330-190) | G75: =J60*5+K60*3.6*0.5-K60*0.5-190*3-(330-190)*3.6-20*2 -> 452.75 | I75: =Q60*5+R60*3*0.5-R60*0.5-190*3-(330-190)*3.6-20*2 -> -24 | K75: =G75*$G$80+I75*$I$80 -> 252.515 | M75: 119.025 | N75: 166.7 | O75: 142.8625 | P75: 190.5375 | Q75: 214.375 | R75: 262.05 | S75: 309.725 | T75: 357.4 | U75: 405.075
D76: Dual order 190, (207-190) | G76: =J61*5+K61*3.6*0.5-K61*0.5-190*3-(207-190)*3.6-20*2 -> 363.8 | I76: =Q61*5+(R61-207+190)*3*0.5+(207-190)*3.6*0.5-R61*0.5-190*3-(207-190)*3.6-20*2 -> 260.77143 | K76: =G76*$G$80+I76*$I$80 -> 320.528 | M76: 291.68 | N76: 301.98286 | O76: 296.83143 | P76: 307.13429 | Q76: 312.28571 | R76: 322.58857 | S76: 332.89143 | T76: 343.19429 | U76: 353.49714
D77: Dual order 207, (352-207) | G77: =J62*5+K62*3.6*0.5-K62*0.5-207*3-(352-207)*3.6-20*2 -> 448.07556 | I77: =Q62*5+R62*3*0.5-R62*0.5-207*3-(352-207)*3.6-20*2 -> -71 | K77: =G77*$G$80+I77*$I$80 -> 230.06382 | M77: 84.722667 | N77: 136.63022 | O77: 110.67644 | P77: 162.584 | Q77: 188.53778 | R77: 240.44533 | S77: 292.35289 | T77: 344.26044 | U77: 396.168
D78: Dual order 207, (330-207) | G78: =J63*5+K63*3.6*0.5-K63*0.5-207*3-(330-207)*3.6-20*2 -> 462.95 | I78: =Q63*5+R63*3*0.5-R63*0.5-207*3-(330-207)*3.6-20*2 -> -13.8 | K78: =G78*$G$80+I78*$I$80 -> 262.715 | M78: 129.225 | N78: 176.9 | O78: 153.0625 | P78: 200.7375 | Q78: 224.575 | R78: 272.25 | S78: 319.925 | T78: 367.6 | U78: 415.275
D79: Dual order 330,(352-330) | G79: =J64*5+(K64-(352-330))*3+(352-330)*3.6*0.5-K64*0.5-330*3-(352-330)*3.6-20*2 -> 537.28889 | I79: =Q64*5+R64*3*0.5-R64*0.5-330*3-(352-330)*3.6-20*2 -> 2.8 | K79: =G79*$G$80+I79*$I$80 -> 312.80356 | M79: 163.14667 | N79: 216.59556 | O79: 189.87111 | P79: 243.32 | Q79: 270.04444 | R79: 323.49333 | S79: 376.94222 | T79: 430.39111 | U79: 483.84
C80: Probability | G80: ='iterations 8 (SL)'!Y31 -> 0.58 | I80: =1-G80 -> 0.42 | K80: =G80 -> 0.58 | L80: D⏐High | M80: 0.3 | N80: 0.4 | O80: 0.35 | P80: 0.45 | Q80: 0.5 | R80: 0.6 | S80: 0.7 | T80: 0.8 | U80: 0.9
A82: (d) | E82: VOSRC= | F82: =K76-'1and2'!J30 -> -49.472
E83: So Not to pay anything

Sheet iterations 8
H2: 5 | I2: 3 | J2: 3.6 | N2: 0.45
B3: Q0 | C3: Q1 | E3: Exp sales | G3: Exp left over | H3: Revenue | I3: Var cost | J3: Var cost | K3: refund cost | L3: ord cost | M3: Profit | N3: exp profit | O3: Q0+Q1
B4: 170 | C4: 0 | E4: High | F4: =IF((240+420)/2>($B4+$C4),($B4+$C4),(240+420)/2) -> 170 | G4: =C4+B4-F4 -> 0 | H4: =F4*$H$2 -> 850 | I4: =$I$2*B4 -> 510 | J4: =$J$2*C4 -> 0 | K4: =-G4*3*0.5+0.5*G4 -> 0 | L4: =2*20 -> 40 | M4: =H4-SUM(I4:L4) -> 300 | N4: =M4*$N$2+M5*(1-$N$2) -> 300 | O4: =B4&"+"&C4 -> 170+0
B5: =B4 -> 170 | C5: =C4 -> 0 | E5: Low | F5: =IF((120+260)/2>($B5+$C5),($B5+$C5),(120+260)/2) -> 170 | G5: =C5+B5-F5 -> 0 | H5: =F5*$H$2 -> 850 | I5: =$I$2*B5 -> 510 | J5: =$J$2*C5 -> 0 | K5: =-G5*3*0.5+0.5*G5 -> 0 | L5: =2*20 -> 40 | M5: =H5-SUM(I5:L5) -> 300 | Q5: 1
B6: =B5 -> 170 | C6: =+C4+10 -> 10 | E6: High | F6: =IF((240+420)/2>($B6+$C6),($B6+$C6),(240+420)/2) -> 180 | G6: =C6+B6-F6 -> 0 | H6: =F6*$H$2 -> 900 | I6: =$I$2*B6 -> 510 | J6: =$J$2*C6 -> 36 | K6: =-G6*3*0.5+0.5*G6 -> 0 | L6: =2*20 -> 40 | M6: =H6-SUM(I6:L6) -> 314 | N6: =M6*$N$2+M7*(1-$N$2) -> 314 | O6: =B6&"+"&C6 -> 170+10 | Q6: 3
B7: =B6 -> 170 | C7: =C6 -> 10 | E7: Low | F7: =IF((120+260)/2>($B7+$C7),($B7+$C7),(120+260)/2) -> 180 | G7: =C7+B7-F7 -> 0 | H7: =F7*$H$2 -> 900 | I7: =$I$2*B7 -> 510 | J7: =$J$2*C7 -> 36 | K7: =-G7*3*0.5+0.5*G7 -> 0 | L7: =2*20 -> 40 | M7: =H7-SUM(I7:L7) -> 314 | Q7: =Q5&"+"&Q6 -> 1+3
B8: =B7 -> 170 | C8: =+C6+10 -> 20 | E8: High | F8: =IF((240+420)/2>($B8+$C8),($B8+$C8),(240+420)/2) -> 190 | G8: =C8+B8-F8 -> 0 | H8: =F8*$H$2 -> 950 | I8: =$I$2*B8 -> 510 | J8: =$J$2*C8 -> 72 | K8: =-G8*3*0.5+0.5*G8 -> 0 | L8: =2*20 -> 40 | M8: =H8-SUM(I8:L8) -> 328 | N8: =M8*$N$2+M9*(1-$N$2) -> 328 | O8: =B8&"+"&C8 -> 170+20
B9: =B8 -> 170 | C9: =C8 -> 20 | E9: Low | F9: =IF((120+260)/2>($B9+$C9),($B9+$C9),(120+260)/2) -> 190 | G9: =C9+B9-F9 -> 0 | H9: =F9*$H$2 -> 950 | I9: =$I$2*B9 -> 510 | J9: =$J$2*C9 -> 72 | K9: =-G9*3*0.5+0.5*G9 -> 0 | L9: =2*20 -> 40 | M9: =H9-SUM(I9:L9) -> 328
B10: =B9 -> 170 | C10: =+C8+10 -> 30 | E10: High | F10: =IF((240+420)/2>($B10+$C10),($B10+$C10),(240+420)/2) -> 200 | G10: =C10+B10-F10 -> 0 | H10: =F10*$H$2 -> 1000 | I10: =$I$2*B10 -> 510 | J10: =$J$2*C10 -> 108 | K10: =-G10*3*0.5+0.5*G10 -> 0 | L10: =2*20 -> 40 | M10: =H10-SUM(I10:L10) -> 342 | N10: =M10*$N$2+M11*(1-$N$2) -> 320 | O10: =B10&"+"&C10 -> 170+30
B11: =B10 -> 170 | C11: =C10 -> 30 | E11: Low | F11: =IF((120+260)/2>($B11+$C11),($B11+$C11),(120+260)/2) -> 190 | G11: =C11+B11-F11 -> 10 | H11: =F11*$H$2 -> 950 | I11: =$I$2*B11 -> 510 | J11: =$J$2*C11 -> 108 | K11: =-G11*3*0.5+0.5*G11 -> -10 | L11: =2*20 -> 40 | M11: =H11-SUM(I11:L11) -> 302
B12: =B11 -> 170 | C12: =+C10+10 -> 40 | E12: High | F12: =IF((240+420)/2>($B12+$C12),($B12+$C12),(240+420)/2) -> 210 | G12: =C12+B12-F12 -> 0 | H12: =F12*$H$2 -> 1050 | I12: =$I$2*B12 -> 510 | J12: =$J$2*C12 -> 144 | K12: =-G12*3*0.5+0.5*G12 -> 0 | L12: =2*20 -> 40 | M12: =H12-SUM(I12:L12) -> 356 | N12: =M12*$N$2+M13*(1-$N$2) -> 312 | O12: =B12&"+"&C12 -> 170+40
B13: =B12 -> 170 | C13: =C12 -> 40 | E13: Low | F13: =IF((120+260)/2>($B13+$C13),($B13+$C13),(120+260)/2) -> 190 | G13: =C13+B13-F13 -> 20 | H13: =F13*$H$2 -> 950 | I13: =$I$2*B13 -> 510 | J13: =$J$2*C13 -> 144 | K13: =-G13*3*0.5+0.5*G13 -> -20 | L13: =2*20 -> 40 | M13: =H13-SUM(I13:L13) -> 276
B14: =B13 -> 170 | C14: =+C12+10 -> 50 | E14: High | F14: =IF((240+420)/2>($B14+$C14),($B14+$C14),(240+420)/2) -> 220 | G14: =C14+B14-F14 -> 0 | H14: =F14*$H$2 -> 1100 | I14: =$I$2*B14 -> 510 | J14: =$J$2*C14 -> 180 | K14: =-G14*3*0.5+0.5*G14 -> 0 | L14: =2*20 -> 40 | M14: =H14-SUM(I14:L14) -> 370 | N14: =M14*$N$2+M15*(1-$N$2) -> 304 | O14: =B14&"+"&C14 -> 170+50
B15: =B14 -> 170 | C15: =C14 -> 50 | E15: Low | F15: =IF((120+260)/2>($B15+$C15),($B15+$C15),(120+260)/2) -> 190 | G15: =C15+B15-F15 -> 30 | H15: =F15*$H$2 -> 950 | I15: =$I$2*B15 -> 510 | J15: =$J$2*C15 -> 180 | K15: =-G15*3*0.5+0.5*G15 -> -30 | L15: =2*20 -> 40 | M15: =H15-SUM(I15:L15) -> 250
B16: =B15 -> 170 | C16: =+C14+10 -> 60 | E16: High | F16: =IF((240+420)/2>($B16+$C16),($B16+$C16),(240+420)/2) -> 230 | G16: =C16+B16-F16 -> 0 | H16: =F16*$H$2 -> 1150 | I16: =$I$2*B16 -> 510 | J16: =$J$2*C16 -> 216 | K16: =-G16*3*0.5+0.5*G16 -> 0 | L16: =2*20 -> 40 | M16: =H16-SUM(I16:L16) -> 384 | N16: =M16*$N$2+M17*(1-$N$2) -> 296 | O16: =B16&"+"&C16 -> 170+60
B17: =B16 -> 170 | C17: =C16 -> 60 | E17: Low | F17: =IF((120+260)/2>($B17+$C17),($B17+$C17),(120+260)/2) -> 190 | G17: =C17+B17-F17 -> 40 | H17: =F17*$H$2 -> 950 | I17: =$I$2*B17 -> 510 | J17: =$J$2*C17 -> 216 | K17: =-G17*3*0.5+0.5*G17 -> -40 | L17: =2*20 -> 40 | M17: =H17-SUM(I17:L17) -> 224
B18: =B17 -> 170 | C18: =+C16+10 -> 70 | E18: High | F18: =IF((240+420)/2>($B18+$C18),($B18+$C18),(240+420)/2) -> 240 | G18: =C18+B18-F18 -> 0 | H18: =F18*$H$2 -> 1200 | I18: =$I$2*B18 -> 510 | J18: =$J$2*C18 -> 252 | K18: =-G18*3*0.5+0.5*G18 -> 0 | L18: =2*20 -> 40 | M18: =H18-SUM(I18:L18) -> 398 | N18: =M18*$N$2+M19*(1-$N$2) -> 288 | O18: =B18&"+"&C18 -> 170+70
B19: =B18 -> 170 | C19: =C18 -> 70 | E19: Low | F19: =IF((120+260)/2>($B19+$C19),($B19+$C19),(120+260)/2) -> 190 | G19: =C19+B19-F19 -> 50 | H19: =F19*$H$2 -> 950 | I19: =$I$2*B19 -> 510 | J19: =$J$2*C19 -> 252 | K19: =-G19*3*0.5+0.5*G19 -> -50 | L19: =2*20 -> 40 | M19: =H19-SUM(I19:L19) -> 198
B20: =B19 -> 170 | C20: =+C18+10 -> 80 | E20: High | F20: =IF((240+420)/2>($B20+$C20),($B20+$C20),(240+420)/2) -> 250 | G20: =C20+B20-F20 -> 0 | H20: =F20*$H$2 -> 1250 | I20: =$I$2*B20 -> 510 | J20: =$J$2*C20 -> 288 | K20: =-G20*3*0.5+0.5*G20 -> 0 | L20: =2*20 -> 40 | M20: =H20-SUM(I20:L20) -> 412 | N20: =M20*$N$2+M21*(1-$N$2) -> 280 | O20: =B20&"+"&C20 -> 170+80
B21: =B20 -> 170 | C21: =C20 -> 80 | E21: Low | F21: =IF((120+260)/2>($B21+$C21),($B21+$C21),(120+260)/2) -> 190 | G21: =C21+B21-F21 -> 60 | H21: =F21*$H$2 -> 950 | I21: =$I$2*B21 -> 510 | J21: =$J$2*C21 -> 288 | K21: =-G21*3*0.5+0.5*G21 -> -60 | L21: =2*20 -> 40 | M21: =H21-SUM(I21:L21) -> 172
B22: =B21 -> 170 | C22: =+C20+10 -> 90 | E22: High | F22: =IF((240+420)/2>($B22+$C22),($B22+$C22),(240+420)/2) -> 260 | G22: =C22+B22-F22 -> 0 | H22: =F22*$H$2 -> 1300 | I22: =$I$2*B22 -> 510 | J22: =$J$2*C22 -> 324 | K22: =-G22*3*0.5+0.5*G22 -> 0 | L22: =2*20 -> 40 | M22: =H22-SUM(I22:L22) -> 426 | N22: =M22*$N$2+M23*(1-$N$2) -> 272 | O22: =B22&"+"&C22 -> 170+90
B23: =B22 -> 170 | C23: =C22 -> 90 | E23: Low | F23: =IF((120+260)/2>($B23+$C23),($B23+$C23),(120+260)/2) -> 190 | G23: =C23+B23-F23 -> 70 | H23: =F23*$H$2 -> 950 | I23: =$I$2*B23 -> 510 | J23: =$J$2*C23 -> 324 | K23: =-G23*3*0.5+0.5*G23 -> -70 | L23: =2*20 -> 40 | M23: =H23-SUM(I23:L23) -> 146
B24: =B23 -> 170 | C24: =+C22+10 -> 100 | E24: High | F24: =IF((240+420)/2>($B24+$C24),($B24+$C24),(240+420)/2) -> 270 | G24: =C24+B24-F24 -> 0 | H24: =F24*$H$2 -> 1350 | I24: =$I$2*B24 -> 510 | J24: =$J$2*C24 -> 360 | K24: =-G24*3*0.5+0.5*G24 -> 0 | L24: =2*20 -> 40 | M24: =H24-SUM(I24:L24) -> 440 | N24: =M24*$N$2+M25*(1-$N$2) -> 264 | O24: =B24&"+"&C24 -> 170+100
B25: =B24 -> 170 | C25: =C24 -> 100 | E25: Low | F25: =IF((120+260)/2>($B25+$C25),($B25+$C25),(120+260)/2) -> 190 | G25: =C25+B25-F25 -> 80 | H25: =F25*$H$2 -> 950 | I25: =$I$2*B25 -> 510 | J25: =$J$2*C25 -> 360 | K25: =-G25*3*0.5+0.5*G25 -> -80 | L25: =2*20 -> 40 | M25: =H25-SUM(I25:L25) -> 120
B26: =B25 -> 170 | C26: =+C24+10 -> 110 | E26: High | F26: =IF((240+420)/2>($B26+$C26),($B26+$C26),(240+420)/2) -> 280 | G26: =C26+B26-F26 -> 0 | H26: =F26*$H$2 -> 1400 | I26: =$I$2*B26 -> 510 | J26: =$J$2*C26 -> 396 | K26: =-G26*3*0.5+0.5*G26 -> 0 | L26: =2*20 -> 40 | M26: =H26-SUM(I26:L26) -> 454 | N26: =M26*$N$2+M27*(1-$N$2) -> 256 | O26: =B26&"+"&C26 -> 170+110
B27: =B26 -> 170 | C27: =C26 -> 110 | E27: Low | F27: =IF((120+260)/2>($B27+$C27),($B27+$C27),(120+260)/2) -> 190 | G27: =C27+B27-F27 -> 90 | H27: =F27*$H$2 -> 950 | I27: =$I$2*B27 -> 510 | J27: =$J$2*C27 -> 396 | K27: =-G27*3*0.5+0.5*G27 -> -90 | L27: =2*20 -> 40 | M27: =H27-SUM(I27:L27) -> 94
B28: =B27 -> 170 | C28: =+C26+10 -> 120 | E28: High | F28: =IF((240+420)/2>($B28+$C28),($B28+$C28),(240+420)/2) -> 290 | G28: =C28+B28-F28 -> 0 | H28: =F28*$H$2 -> 1450 | I28: =$I$2*B28 -> 510 | J28: =$J$2*C28 -> 432 | K28: =-G28*3*0.5+0.5*G28 -> 0 | L28: =2*20 -> 40 | M28: =H28-SUM(I28:L28) -> 468 | N28: =M28*$N$2+M29*(1-$N$2) -> 248 | O28: =B28&"+"&C28 -> 170+120
B29: =B28 -> 170 | C29: =C28 -> 120 | E29: Low | F29: =IF((120+260)/2>($B29+$C29),($B29+$C29),(120+260)/2) -> 190 | G29: =C29+B29-F29 -> 100 | H29: =F29*$H$2 -> 950 | I29: =$I$2*B29 -> 510 | J29: =$J$2*C29 -> 432 | K29: =-G29*3*0.5+0.5*G29 -> -100 | L29: =2*20 -> 40 | M29: =H29-SUM(I29:L29) -> 68
B30: =B29 -> 170 | C30: =+C28+10 -> 130 | E30: High | F30: =IF((240+420)/2>($B30+$C30),($B30+$C30),(240+420)/2) -> 300 | G30: =C30+B30-F30 -> 0 | H30: =F30*$H$2 -> 1500 | I30: =$I$2*B30 -> 510 | J30: =$J$2*C30 -> 468 | K30: =-G30*3*0.5+0.5*G30 -> 0 | L30: =2*20 -> 40 | M30: =H30-SUM(I30:L30) -> 482 | N30: =M30*$N$2+M31*(1-$N$2) -> 240 | O30: =B30&"+"&C30 -> 170+130
B31: =B30 -> 170 | C31: =C30 -> 130 | E31: Low | F31: =IF((120+260)/2>($B31+$C31),($B31+$C31),(120+260)/2) -> 190 | G31: =C31+B31-F31 -> 110 | H31: =F31*$H$2 -> 950 | I31: =$I$2*B31 -> 510 | J31: =$J$2*C31 -> 468 | K31: =-G31*3*0.5+0.5*G31 -> -110 | L31: =2*20 -> 40 | M31: =H31-SUM(I31:L31) -> 42
B32: =B31 -> 170 | C32: =+C30+10 -> 140 | E32: High | F32: =IF((240+420)/2>($B32+$C32),($B32+$C32),(240+420)/2) -> 310 | G32: =C32+B32-F32 -> 0 | H32: =F32*$H$2 -> 1550 | I32: =$I$2*B32 -> 510 | J32: =$J$2*C32 -> 504 | K32: =-G32*3*0.5+0.5*G32 -> 0 | L32: =2*20 -> 40 | M32: =H32-SUM(I32:L32) -> 496 | N32: =M32*$N$2+M33*(1-$N$2) -> 232 | O32: =B32&"+"&C32 -> 170+140
B33: =B32 -> 170 | C33: =C32 -> 140 | E33: Low | F33: =IF((120+260)/2>($B33+$C33),($B33+$C33),(120+260)/2) -> 190 | G33: =C33+B33-F33 -> 120 | H33: =F33*$H$2 -> 950 | I33: =$I$2*B33 -> 510 | J33: =$J$2*C33 -> 504 | K33: =-G33*3*0.5+0.5*G33 -> -120 | L33: =2*20 -> 40 | M33: =H33-SUM(I33:L33) -> 16
B34: =B33 -> 170 | C34: =+C32+10 -> 150 | E34: High | F34: =IF((240+420)/2>($B34+$C34),($B34+$C34),(240+420)/2) -> 320 | G34: =C34+B34-F34 -> 0 | H34: =F34*$H$2 -> 1600 | I34: =$I$2*B34 -> 510 | J34: =$J$2*C34 -> 540 | K34: =-G34*3*0.5+0.5*G34 -> 0 | L34: =2*20 -> 40 | M34: =H34-SUM(I34:L34) -> 510 | N34: =M34*$N$2+M35*(1-$N$2) -> 224 | O34: =B34&"+"&C34 -> 170+150
B35: =B34 -> 170 | C35: =C34 -> 150 | E35: Low | F35: =IF((120+260)/2>($B35+$C35),($B35+$C35),(120+260)/2) -> 190 | G35: =C35+B35-F35 -> 130 | H35: =F35*$H$2 -> 950 | I35: =$I$2*B35 -> 510 | J35: =$J$2*C35 -> 540 | K35: =-G35*3*0.5+0.5*G35 -> -130 | L35: =2*20 -> 40 | M35: =H35-SUM(I35:L35) -> -10
B36: =B35 -> 170 | C36: =+C34+10 -> 160 | E36: High | F36: =IF((240+420)/2>($B36+$C36),($B36+$C36),(240+420)/2) -> 330 | G36: =C36+B36-F36 -> 0 | H36: =F36*$H$2 -> 1650 | I36: =$I$2*B36 -> 510 | J36: =$J$2*C36 -> 576 | K36: =-G36*3*0.5+0.5*G36 -> 0 | L36: =2*20 -> 40 | M36: =H36-SUM(I36:L36) -> 524 | N36: =M36*$N$2+M37*(1-$N$2) -> 216 | O36: =B36&"+"&C36 -> 170+160
B37: =B36 -> 170 | C37: =C36 -> 160 | E37: Low | F37: =IF((120+260)/2>($B37+$C37),($B37+$C37),(120+260)/2) -> 190 | G37: =C37+B37-F37 -> 140 | H37: =F37*$H$2 -> 950 | I37: =$I$2*B37 -> 510 | J37: =$J$2*C37 -> 576 | K37: =-G37*3*0.5+0.5*G37 -> -140 | L37: =2*20 -> 40 | M37: =H37-SUM(I37:L37) -> -36
B38: =B37 -> 170 | C38: =+C36+10 -> 170 | E38: High | F38: =IF((240+420)/2>($B38+$C38),($B38+$C38),(240+420)/2) -> 330 | G38: =C38+B38-F38 -> 10 | H38: =F38*$H$2 -> 1650 | I38: =$I$2*B38 -> 510 | J38: =$J$2*C38 -> 612 | K38: =-G38*3*0.5+0.5*G38 -> -10 | L38: =2*20 -> 40 | M38: =H38-SUM(I38:L38) -> 498 | N38: =M38*$N$2+M39*(1-$N$2) -> 190 | O38: =B38&"+"&C38 -> 170+170
B39: =B38 -> 170 | C39: =C38 -> 170 | E39: Low | F39: =IF((120+260)/2>($B39+$C39),($B39+$C39),(120+260)/2) -> 190 | G39: =C39+B39-F39 -> 150 | H39: =F39*$H$2 -> 950 | I39: =$I$2*B39 -> 510 | J39: =$J$2*C39 -> 612 | K39: =-G39*3*0.5+0.5*G39 -> -150 | L39: =2*20 -> 40 | M39: =H39-SUM(I39:L39) -> -62
B40: =B39 -> 170 | C40: =+C38+10 -> 180 | E40: High | F40: =IF((240+420)/2>($B40+$C40),($B40+$C40),(240+420)/2) -> 330 | G40: =C40+B40-F40 -> 20 | H40: =F40*$H$2 -> 1650 | I40: =$I$2*B40 -> 510 | J40: =$J$2*C40 -> 648 | K40: =-G40*3*0.5+0.5*G40 -> -20 | L40: =2*20 -> 40 | M40: =H40-SUM(I40:L40) -> 472 | N40: =M40*$N$2+M41*(1-$N$2) -> 164 | O40: =B40&"+"&C40 -> 170+180
B41: =B40 -> 170 | C41: =C40 -> 180 | E41: Low | F41: =IF((120+260)/2>($B41+$C41),($B41+$C41),(120+260)/2) -> 190 | G41: =C41+B41-F41 -> 160 | H41: =F41*$H$2 -> 950 | I41: =$I$2*B41 -> 510 | J41: =$J$2*C41 -> 648 | K41: =-G41*3*0.5+0.5*G41 -> -160 | L41: =2*20 -> 40 | M41: =H41-SUM(I41:L41) -> -88
B42: =B41 -> 170 | C42: =+C40+10 -> 190 | E42: High | F42: =IF((240+420)/2>($B42+$C42),($B42+$C42),(240+420)/2) -> 330 | G42: =C42+B42-F42 -> 30 | H42: =F42*$H$2 -> 1650 | I42: =$I$2*B42 -> 510 | J42: =$J$2*C42 -> 684 | K42: =-G42*3*0.5+0.5*G42 -> -30 | L42: =2*20 -> 40 | M42: =H42-SUM(I42:L42) -> 446 | N42: =M42*$N$2+M43*(1-$N$2) -> 138 | O42: =B42&"+"&C42 -> 170+190
B43: =B42 -> 170 | C43: =C42 -> 190 | E43: Low | F43: =IF((120+260)/2>($B43+$C43),($B43+$C43),(120+260)/2) -> 190 | G43: =C43+B43-F43 -> 170 | H43: =F43*$H$2 -> 950 | I43: =$I$2*B43 -> 510 | J43: =$J$2*C43 -> 684 | K43: =-G43*3*0.5+0.5*G43 -> -170 | L43: =2*20 -> 40 | M43: =H43-SUM(I43:L43) -> -114
B44: =B43 -> 170 | C44: =+C42+10 -> 200 | E44: High | F44: =IF((240+420)/2>($B44+$C44),($B44+$C44),(240+420)/2) -> 330 | G44: =C44+B44-F44 -> 40 | H44: =F44*$H$2 -> 1650 | I44: =$I$2*B44 -> 510 | J44: =$J$2*C44 -> 720 | K44: =-G44*3*0.5+0.5*G44 -> -40 | L44: =2*20 -> 40 | M44: =H44-SUM(I44:L44) -> 420 | N44: =M44*$N$2+M45*(1-$N$2) -> 112 | O44: =B44&"+"&C44 -> 170+200
B45: =B44 -> 170 | C45: =C44 -> 200 | E45: Low | F45: =IF((120+260)/2>($B45+$C45),($B45+$C45),(120+260)/2) -> 190 | G45: =C45+B45-F45 -> 180 | H45: =F45*$H$2 -> 950 | I45: =$I$2*B45 -> 510 | J45: =$J$2*C45 -> 720 | K45: =-G45*3*0.5+0.5*G45 -> -180 | L45: =2*20 -> 40 | M45: =H45-SUM(I45:L45) -> -140

Sheet iterations 8 (SH)
M1: Assumption
H2: 5 | I2: 3 | J2: 3.6 | M2: P(D=H⏐S=H) | N2: 0.8
B3: Q0 | C3: Q1 | E3: Exp sales | G3: Exp left over | H3: Revenue | I3: Var cost | J3: Var cost | K3: refund cost | L3: ord cost | M3: Profit | N3: exp profit | O3: Q0+Q1
A4: 1 | B4: 330 | C4: 0 | E4: High | F4: =IF((240+420)/2>($B4+$C4),($B4+$C4),(240+420)/2) -> 330 | G4: =C4+B4-F4 -> 0 | H4: =F4*$H$2 -> 1650 | I4: =$I$2*B4 -> 990 | J4: =$J$2*C4 -> 0 | K4: =-G4*3*0.5+0.5*G4 -> 0 | L4: =2*20 -> 40 | M4: =H4-SUM(I4:L4) -> 620 | N4: =M4*$N$2+M5*(1-$N$2) -> 508 | O4: =B4&"+"&C4 -> 330+0 | P4: =N4*N2 -> 406.4
B5: =B4 -> 330 | C5: =C4 -> 0 | E5: Low | F5: =IF((120+260)/2>($B5+$C5),($B5+$C5),(120+260)/2) -> 190 | G5: =C5+B5-F5 -> 140 | H5: =F5*$H$2 -> 950 | I5: =$I$2*B5 -> 990 | J5: =$J$2*C5 -> 0 | K5: =-G5*3*0.5+0.5*G5 -> -140 | L5: =2*20 -> 40 | M5: =H5-SUM(I5:L5) -> 60 | Q5: 170
A6: =A4+2 -> 3 | B6: =B5 -> 330 | C6: =+C4+10 -> 10 | E6: High | F6: =IF((240+420)/2>($B6+$C6),($B6+$C6),(240+420)/2) -> 330 | G6: =C6+B6-F6 -> 10 | H6: =F6*$H$2 -> 1650 | I6: =$I$2*B6 -> 990 | J6: =$J$2*C6 -> 36 | K6: =-G6*3*0.5+0.5*G6 -> -10 | L6: =2*20 -> 40 | M6: =H6-SUM(I6:L6) -> 594 | N6: =M6*$N$2+M7*(1-$N$2) -> 482 | O6: =B6&"+"&C6 -> 330+10 | Q6: =Q5+10 -> 180
B7: =B6 -> 330 | C7: =C6 -> 10 | E7: Low | F7: =IF((120+260)/2>($B7+$C7),($B7+$C7),(120+260)/2) -> 190 | G7: =C7+B7-F7 -> 150 | H7: =F7*$H$2 -> 950 | I7: =$I$2*B7 -> 990 | J7: =$J$2*C7 -> 36 | K7: =-G7*3*0.5+0.5*G7 -> -150 | L7: =2*20 -> 40 | M7: =H7-SUM(I7:L7) -> 34 | Q7: =Q6+10 -> 190
A8: =A6+2 -> 5 | B8: =B7 -> 330 | C8: =+C6+10 -> 20 | E8: High | F8: =IF((240+420)/2>($B8+$C8),($B8+$C8),(240+420)/2) -> 330 | G8: =C8+B8-F8 -> 20 | H8: =F8*$H$2 -> 1650 | I8: =$I$2*B8 -> 990 | J8: =$J$2*C8 -> 72 | K8: =-G8*3*0.5+0.5*G8 -> -20 | L8: =2*20 -> 40 | M8: =H8-SUM(I8:L8) -> 568 | N8: =M8*$N$2+M9*(1-$N$2) -> 456 | O8: =B8&"+"&C8 -> 330+20 | Q8: =Q7+10 -> 200
B9: =B8 -> 330 | C9: =C8 -> 20 | E9: Low | F9: =IF((120+260)/2>($B9+$C9),($B9+$C9),(120+260)/2) -> 190 | G9: =C9+B9-F9 -> 160 | H9: =F9*$H$2 -> 950 | I9: =$I$2*B9 -> 990 | J9: =$J$2*C9 -> 72 | K9: =-G9*3*0.5+0.5*G9 -> -160 | L9: =2*20 -> 40 | M9: =H9-SUM(I9:L9) -> 8 | Q9: =Q8+10 -> 210
A10: =A8+2 -> 7 | B10: =B9 -> 330 | C10: =+C8+10 -> 30 | E10: High | F10: =IF((240+420)/2>($B10+$C10),($B10+$C10),(240+420)/2) -> 330 | G10: =C10+B10-F10 -> 30 | H10: =F10*$H$2 -> 1650 | I10: =$I$2*B10 -> 990 | J10: =$J$2*C10 -> 108 | K10: =-G10*3*0.5+0.5*G10 -> -30 | L10: =2*20 -> 40 | M10: =H10-SUM(I10:L10) -> 542 | N10: =M10*$N$2+M11*(1-$N$2) -> 430 | O10: =B10&"+"&C10 -> 330+30 | Q10: =Q9+10 -> 220
B11: =B10 -> 330 | C11: =C10 -> 30 | E11: Low | F11: =IF((120+260)/2>($B11+$C11),($B11+$C11),(120+260)/2) -> 190 | G11: =C11+B11-F11 -> 170 | H11: =F11*$H$2 -> 950 | I11: =$I$2*B11 -> 990 | J11: =$J$2*C11 -> 108 | K11: =-G11*3*0.5+0.5*G11 -> -170 | L11: =2*20 -> 40 | M11: =H11-SUM(I11:L11) -> -18 | Q11: =Q10+10 -> 230
A12: =A10+2 -> 9 | B12: =B11 -> 330 | C12: =+C10+10 -> 40 | E12: High | F12: =IF((240+420)/2>($B12+$C12),($B12+$C12),(240+420)/2) -> 330 | G12: =C12+B12-F12 -> 40 | H12: =F12*$H$2 -> 1650 | I12: =$I$2*B12 -> 990 | J12: =$J$2*C12 -> 144 | K12: =-G12*3*0.5+0.5*G12 -> -40 | L12: =2*20 -> 40 | M12: =H12-SUM(I12:L12) -> 516 | N12: =M12*$N$2+M13*(1-$N$2) -> 404 | O12: =B12&"+"&C12 -> 330+40 | Q12: =Q11+10 -> 240
B13: =B12 -> 330 | C13: =C12 -> 40 | E13: Low | F13: =IF((120+260)/2>($B13+$C13),($B13+$C13),(120+260)/2) -> 190 | G13: =C13+B13-F13 -> 180 | H13: =F13*$H$2 -> 950 | I13: =$I$2*B13 -> 990 | J13: =$J$2*C13 -> 144 | K13: =-G13*3*0.5+0.5*G13 -> -180 | L13: =2*20 -> 40 | M13: =H13-SUM(I13:L13) -> -44 | Q13: =Q12+10 -> 250
A14: =A12+2 -> 11 | B14: =B13 -> 330 | C14: =+C12+10 -> 50 | E14: High | F14: =IF((240+420)/2>($B14+$C14),($B14+$C14),(240+420)/2) -> 330 | G14: =C14+B14-F14 -> 50 | H14: =F14*$H$2 -> 1650 | I14: =$I$2*B14 -> 990 | J14: =$J$2*C14 -> 180 | K14: =-G14*3*0.5+0.5*G14 -> -50 | L14: =2*20 -> 40 | M14: =H14-SUM(I14:L14) -> 490 | N14: =M14*$N$2+M15*(1-$N$2) -> 378 | O14: =B14&"+"&C14 -> 330+50 | Q14: =Q13+10 -> 260
B15: =B14 -> 330 | C15: =C14 -> 50 | E15: Low | F15: =IF((120+260)/2>($B15+$C15),($B15+$C15),(120+260)/2) -> 190 | G15: =C15+B15-F15 -> 190 | H15: =F15*$H$2 -> 950 | I15: =$I$2*B15 -> 990 | J15: =$J$2*C15 -> 180 | K15: =-G15*3*0.5+0.5*G15 -> -190 | L15: =2*20 -> 40 | M15: =H15-SUM(I15:L15) -> -70 | Q15: =Q14+10 -> 270
A16: =A14+2 -> 13 | B16: =B15 -> 330 | C16: =+C14+10 -> 60 | E16: High | F16: =IF((240+420)/2>($B16+$C16),($B16+$C16),(240+420)/2) -> 330 | G16: =C16+B16-F16 -> 60 | H16: =F16*$H$2 -> 1650 | I16: =$I$2*B16 -> 990 | J16: =$J$2*C16 -> 216 | K16: =-G16*3*0.5+0.5*G16 -> -60 | L16: =2*20 -> 40 | M16: =H16-SUM(I16:L16) -> 464 | N16: =M16*$N$2+M17*(1-$N$2) -> 352 | O16: =B16&"+"&C16 -> 330+60 | Q16: =Q15+10 -> 280
B17: =B16 -> 330 | C17: =C16 -> 60 | E17: Low | F17: =IF((120+260)/2>($B17+$C17),($B17+$C17),(120+260)/2) -> 190 | G17: =C17+B17-F17 -> 200 | H17: =F17*$H$2 -> 950 | I17: =$I$2*B17 -> 990 | J17: =$J$2*C17 -> 216 | K17: =-G17*3*0.5+0.5*G17 -> -200 | L17: =2*20 -> 40 | M17: =H17-SUM(I17:L17) -> -96 | Q17: =Q16+10 -> 290
A18: =A16+2 -> 15 | B18: =B17 -> 330 | C18: =+C16+10 -> 70 | E18: High | F18: =IF((240+420)/2>($B18+$C18),($B18+$C18),(240+420)/2) -> 330 | G18: =C18+B18-F18 -> 70 | H18: =F18*$H$2 -> 1650 | I18: =$I$2*B18 -> 990 | J18: =$J$2*C18 -> 252 | K18: =-G18*3*0.5+0.5*G18 -> -70 | L18: =2*20 -> 40 | M18: =H18-SUM(I18:L18) -> 438 | N18: =M18*$N$2+M19*(1-$N$2) -> 326 | O18: =B18&"+"&C18 -> 330+70 | Q18: =Q17+10 -> 300
B19: =B18 -> 330 | C19: =C18 -> 70 | E19: Low | F19: =IF((120+260)/2>($B19+$C19),($B19+$C19),(120+260)/2) -> 190 | G19: =C19+B19-F19 -> 210 | H19: =F19*$H$2 -> 950 | I19: =$I$2*B19 -> 990 | J19: =$J$2*C19 -> 252 | K19: =-G19*3*0.5+0.5*G19 -> -210 | L19: =2*20 -> 40 | M19: =H19-SUM(I19:L19) -> -122 | Q19: =Q18+10 -> 310
A20: =A18+2 -> 17 | B20: =B19 -> 330 | C20: =+C18+10 -> 80 | E20: High | F20: =IF((240+420)/2>($B20+$C20),($B20+$C20),(240+420)/2) -> 330 | G20: =C20+B20-F20 -> 80 | H20: =F20*$H$2 -> 1650 | I20: =$I$2*B20 -> 990 | J20: =$J$2*C20 -> 288 | K20: =-G20*3*0.5+0.5*G20 -> -80 | L20: =2*20 -> 40 | M20: =H20-SUM(I20:L20) -> 412 | N20: =M20*$N$2+M21*(1-$N$2) -> 300 | O20: =B20&"+"&C20 -> 330+80 | Q20: =Q19+10 -> 320
B21: =B20 -> 330 | C21: =C20 -> 80 | E21: Low | F21: =IF((120+260)/2>($B21+$C21),($B21+$C21),(120+260)/2) -> 190 | G21: =C21+B21-F21 -> 220 | H21: =F21*$H$2 -> 950 | I21: =$I$2*B21 -> 990 | J21: =$J$2*C21 -> 288 | K21: =-G21*3*0.5+0.5*G21 -> -220 | L21: =2*20 -> 40 | M21: =H21-SUM(I21:L21) -> -148 | Q21: =Q20+10 -> 330
A22: =A20+2 -> 19 | B22: =B21 -> 330 | C22: =+C20+10 -> 90 | E22: High | F22: =IF((240+420)/2>($B22+$C22),($B22+$C22),(240+420)/2) -> 330 | G22: =C22+B22-F22 -> 90 | H22: =F22*$H$2 -> 1650 | I22: =$I$2*B22 -> 990 | J22: =$J$2*C22 -> 324 | K22: =-G22*3*0.5+0.5*G22 -> -90 | L22: =2*20 -> 40 | M22: =H22-SUM(I22:L22) -> 386 | N22: =M22*$N$2+M23*(1-$N$2) -> 274 | O22: =B22&"+"&C22 -> 330+90 | Q22: =Q21+10 -> 340
B23: =B22 -> 330 | C23: =C22 -> 90 | E23: Low | F23: =IF((120+260)/2>($B23+$C23),($B23+$C23),(120+260)/2) -> 190 | G23: =C23+B23-F23 -> 230 | H23: =F23*$H$2 -> 950 | I23: =$I$2*B23 -> 990 | J23: =$J$2*C23 -> 324 | K23: =-G23*3*0.5+0.5*G23 -> -230 | L23: =2*20 -> 40 | M23: =H23-SUM(I23:L23) -> -174 | Q23: =Q22+10 -> 350
A24: =A22+2 -> 21 | B24: =B23 -> 330 | C24: =+C22+10 -> 100 | E24: High | F24: =IF((240+420)/2>($B24+$C24),($B24+$C24),(240+420)/2) -> 330 | G24: =C24+B24-F24 -> 100 | H24: =F24*$H$2 -> 1650 | I24: =$I$2*B24 -> 990 | J24: =$J$2*C24 -> 360 | K24: =-G24*3*0.5+0.5*G24 -> -100 | L24: =2*20 -> 40 | M24: =H24-SUM(I24:L24) -> 360 | N24: =M24*$N$2+M25*(1-$N$2) -> 248 | O24: =B24&"+"&C24 -> 330+100 | Q24: =Q23+10 -> 360
B25: =B24 -> 330 | C25: =C24 -> 100 | E25: Low | F25: =IF((120+260)/2>($B25+$C25),($B25+$C25),(120+260)/2) -> 190 | G25: =C25+B25-F25 -> 240 | H25: =F25*$H$2 -> 950 | I25: =$I$2*B25 -> 990 | J25: =$J$2*C25 -> 360 | K25: =-G25*3*0.5+0.5*G25 -> -240 | L25: =2*20 -> 40 | M25: =H25-SUM(I25:L25) -> -200 | Q25: =Q24+10 -> 370
A26: =A24+2 -> 23 | B26: =B25 -> 330 | C26: =+C24+10 -> 110 | E26: High | F26: =IF((240+420)/2>($B26+$C26),($B26+$C26),(240+420)/2) -> 330 | G26: =C26+B26-F26 -> 110 | H26: =F26*$H$2 -> 1650 | I26: =$I$2*B26 -> 990 | J26: =$J$2*C26 -> 396 | K26: =-G26*3*0.5+0.5*G26 -> -110 | L26: =2*20 -> 40 | M26: =H26-SUM(I26:L26) -> 334 | N26: =M26*$N$2+M27*(1-$N$2) -> 222 | O26: =B26&"+"&C26 -> 330+110 | Q26: =Q25+10 -> 380
B27: =B26 -> 330 | C27: =C26 -> 110 | E27: Low | F27: =IF((120+260)/2>($B27+$C27),($B27+$C27),(120+260)/2) -> 190 | G27: =C27+B27-F27 -> 250 | H27: =F27*$H$2 -> 950 | I27: =$I$2*B27 -> 990 | J27: =$J$2*C27 -> 396 | K27: =-G27*3*0.5+0.5*G27 -> -250 | L27: =2*20 -> 40 | M27: =H27-SUM(I27:L27) -> -226 | Q27: =Q26+10 -> 390
A28: =A26+2 -> 25 | B28: =B27 -> 330 | C28: =+C26+10 -> 120 | E28: High | F28: =IF((240+420)/2>($B28+$C28),($B28+$C28),(240+420)/2) -> 330 | G28: =C28+B28-F28 -> 120 | H28: =F28*$H$2 -> 1650 | I28: =$I$2*B28 -> 990 | J28: =$J$2*C28 -> 432 | K28: =-G28*3*0.5+0.5*G28 -> -120 | L28: =2*20 -> 40 | M28: =H28-SUM(I28:L28) -> 308 | N28: =M28*$N$2+M29*(1-$N$2) -> 196 | O28: =B28&"+"&C28 -> 330+120 | Q28: =Q27+10 -> 400
B29: =B28 -> 330 | C29: =C28 -> 120 | E29: Low | F29: =IF((120+260)/2>($B29+$C29),($B29+$C29),(120+260)/2) -> 190 | G29: =C29+B29-F29 -> 260 | H29: =F29*$H$2 -> 950 | I29: =$I$2*B29 -> 990 | J29: =$J$2*C29 -> 432 | K29: =-G29*3*0.5+0.5*G29 -> -260 | L29: =2*20 -> 40 | M29: =H29-SUM(I29:L29) -> -252 | Q29: =Q28+10 -> 410
A30: =A28+2 -> 27 | B30: =B29 -> 330 | C30: =+C28+10 -> 130 | E30: High | F30: =IF((240+420)/2>($B30+$C30),($B30+$C30),(240+420)/2) -> 330 | G30: =C30+B30-F30 -> 130 | H30: =F30*$H$2 -> 1650 | I30: =$I$2*B30 -> 990 | J30: =$J$2*C30 -> 468 | K30: =-G30*3*0.5+0.5*G30 -> -130 | L30: =2*20 -> 40 | M30: =H30-SUM(I30:L30) -> 282 | N30: =M30*$N$2+M31*(1-$N$2) -> 170 | O30: =B30&"+"&C30 -> 330+130 | Q30: =Q29+10 -> 420
B31: =B30 -> 330 | C31: =C30 -> 130 | E31: Low | F31: =IF((120+260)/2>($B31+$C31),($B31+$C31),(120+260)/2) -> 190 | G31: =C31+B31-F31 -> 270 | H31: =F31*$H$2 -> 950 | I31: =$I$2*B31 -> 990 | J31: =$J$2*C31 -> 468 | K31: =-G31*3*0.5+0.5*G31 -> -270 | L31: =2*20 -> 40 | M31: =H31-SUM(I31:L31) -> -278
A32: =A30+2 -> 29 | B32: =B31 -> 330 | C32: =+C30+10 -> 140 | E32: High | F32: =IF((240+420)/2>($B32+$C32),($B32+$C32),(240+420)/2) -> 330 | G32: =C32+B32-F32 -> 140 | H32: =F32*$H$2 -> 1650 | I32: =$I$2*B32 -> 990 | J32: =$J$2*C32 -> 504 | K32: =-G32*3*0.5+0.5*G32 -> -140 | L32: =2*20 -> 40 | M32: =H32-SUM(I32:L32) -> 256 | N32: =M32*$N$2+M33*(1-$N$2) -> 144 | O32: =B32&"+"&C32 -> 330+140
B33: =B32 -> 330 | C33: =C32 -> 140 | E33: Low | F33: =IF((120+260)/2>($B33+$C33),($B33+$C33),(120+260)/2) -> 190 | G33: =C33+B33-F33 -> 280 | H33: =F33*$H$2 -> 950 | I33: =$I$2*B33 -> 990 | J33: =$J$2*C33 -> 504 | K33: =-G33*3*0.5+0.5*G33 -> -280 | L33: =2*20 -> 40 | M33: =H33-SUM(I33:L33) -> -304
A34: =A32+2 -> 31 | B34: =B33 -> 330 | C34: =+C32+10 -> 150 | E34: High | F34: =IF((240+420)/2>($B34+$C34),($B34+$C34),(240+420)/2) -> 330 | G34: =C34+B34-F34 -> 150 | H34: =F34*$H$2 -> 1650 | I34: =$I$2*B34 -> 990 | J34: =$J$2*C34 -> 540 | K34: =-G34*3*0.5+0.5*G34 -> -150 | L34: =2*20 -> 40 | M34: =H34-SUM(I34:L34) -> 230 | N34: =M34*$N$2+M35*(1-$N$2) -> 118 | O34: =B34&"+"&C34 -> 330+150
B35: =B34 -> 330 | C35: =C34 -> 150 | E35: Low | F35: =IF((120+260)/2>($B35+$C35),($B35+$C35),(120+260)/2) -> 190 | G35: =C35+B35-F35 -> 290 | H35: =F35*$H$2 -> 950 | I35: =$I$2*B35 -> 990 | J35: =$J$2*C35 -> 540 | K35: =-G35*3*0.5+0.5*G35 -> -290 | L35: =2*20 -> 40 | M35: =H35-SUM(I35:L35) -> -330
A36: =A34+2 -> 33 | B36: =B35 -> 330 | C36: =+C34+10 -> 160 | E36: High | F36: =IF((240+420)/2>($B36+$C36),($B36+$C36),(240+420)/2) -> 330 | G36: =C36+B36-F36 -> 160 | H36: =F36*$H$2 -> 1650 | I36: =$I$2*B36 -> 990 | J36: =$J$2*C36 -> 576 | K36: =-G36*3*0.5+0.5*G36 -> -160 | L36: =2*20 -> 40 | M36: =H36-SUM(I36:L36) -> 204 | N36: =M36*$N$2+M37*(1-$N$2) -> 92 | O36: =B36&"+"&C36 -> 330+160
B37: =B36 -> 330 | C37: =C36 -> 160 | E37: Low | F37: =IF((120+260)/2>($B37+$C37),($B37+$C37),(120+260)/2) -> 190 | G37: =C37+B37-F37 -> 300 | H37: =F37*$H$2 -> 950 | I37: =$I$2*B37 -> 990 | J37: =$J$2*C37 -> 576 | K37: =-G37*3*0.5+0.5*G37 -> -300 | L37: =2*20 -> 40 | M37: =H37-SUM(I37:L37) -> -356
A38: =A36+2 -> 35 | B38: =B37 -> 330 | C38: =+C36+10 -> 170 | E38: High | F38: =IF((240+420)/2>($B38+$C38),($B38+$C38),(240+420)/2) -> 330 | G38: =C38+B38-F38 -> 170 | H38: =F38*$H$2 -> 1650 | I38: =$I$2*B38 -> 990 | J38: =$J$2*C38 -> 612 | K38: =-G38*3*0.5+0.5*G38 -> -170 | L38: =2*20 -> 40 | M38: =H38-SUM(I38:L38) -> 178 | N38: =M38*$N$2+M39*(1-$N$2) -> 66 | O38: =B38&"+"&C38 -> 330+170
B39: =B38 -> 330 | C39: =C38 -> 170 | E39: Low | F39: =IF((120+260)/2>($B39+$C39),($B39+$C39),(120+260)/2) -> 190 | G39: =C39+B39-F39 -> 310 | H39: =F39*$H$2 -> 950 | I39: =$I$2*B39 -> 990 | J39: =$J$2*C39 -> 612 | K39: =-G39*3*0.5+0.5*G39 -> -310 | L39: =2*20 -> 40 | M39: =H39-SUM(I39:L39) -> -382
A40: =A38+2 -> 37 | B40: =B39 -> 330 | C40: =+C38+10 -> 180 | E40: High | F40: =IF((240+420)/2>($B40+$C40),($B40+$C40),(240+420)/2) -> 330 | G40: =C40+B40-F40 -> 180 | H40: =F40*$H$2 -> 1650 | I40: =$I$2*B40 -> 990 | J40: =$J$2*C40 -> 648 | K40: =-G40*3*0.5+0.5*G40 -> -180 | L40: =2*20 -> 40 | M40: =H40-SUM(I40:L40) -> 152 | N40: =M40*$N$2+M41*(1-$N$2) -> 40 | O40: =B40&"+"&C40 -> 330+180
B41: =B40 -> 330 | C41: =C40 -> 180 | E41: Low | F41: =IF((120+260)/2>($B41+$C41),($B41+$C41),(120+260)/2) -> 190 | G41: =C41+B41-F41 -> 320 | H41: =F41*$H$2 -> 950 | I41: =$I$2*B41 -> 990 | J41: =$J$2*C41 -> 648 | K41: =-G41*3*0.5+0.5*G41 -> -320 | L41: =2*20 -> 40 | M41: =H41-SUM(I41:L41) -> -408
A42: =A40+2 -> 39 | B42: =B41 -> 330 | C42: =+C40+10 -> 190 | E42: High | F42: =IF((240+420)/2>($B42+$C42),($B42+$C42),(240+420)/2) -> 330 | G42: =C42+B42-F42 -> 190 | H42: =F42*$H$2 -> 1650 | I42: =$I$2*B42 -> 990 | J42: =$J$2*C42 -> 684 | K42: =-G42*3*0.5+0.5*G42 -> -190 | L42: =2*20 -> 40 | M42: =H42-SUM(I42:L42) -> 126 | N42: =M42*$N$2+M43*(1-$N$2) -> 14 | O42: =B42&"+"&C42 -> 330+190
B43: =B42 -> 330 | C43: =C42 -> 190 | E43: Low | F43: =IF((120+260)/2>($B43+$C43),($B43+$C43),(120+260)/2) -> 190 | G43: =C43+B43-F43 -> 330 | H43: =F43*$H$2 -> 950 | I43: =$I$2*B43 -> 990 | J43: =$J$2*C43 -> 684 | K43: =-G43*3*0.5+0.5*G43 -> -330 | L43: =2*20 -> 40 | M43: =H43-SUM(I43:L43) -> -434
A44: =A42+2 -> 41 | B44: =B43 -> 330 | C44: =+C42+10 -> 200 | E44: High | F44: =IF((240+420)/2>($B44+$C44),($B44+$C44),(240+420)/2) -> 330 | G44: =C44+B44-F44 -> 200 | H44: =F44*$H$2 -> 1650 | I44: =$I$2*B44 -> 990 | J44: =$J$2*C44 -> 720 | K44: =-G44*3*0.5+0.5*G44 -> -200 | L44: =2*20 -> 40 | M44: =H44-SUM(I44:L44) -> 100 | N44: =M44*$N$2+M45*(1-$N$2) -> -12 | O44: =B44&"+"&C44 -> 330+200
B45: =B44 -> 330 | C45: =C44 -> 200 | E45: Low | F45: =IF((120+260)/2>($B45+$C45),($B45+$C45),(120+260)/2) -> 190 | G45: =C45+B45-F45 -> 340 | H45: =F45*$H$2 -> 950 | I45: =$I$2*B45 -> 990 | J45: =$J$2*C45 -> 720 | K45: =-G45*3*0.5+0.5*G45 -> -340 | L45: =2*20 -> 40 | M45: =H45-SUM(I45:L45) -> -460
A46: =A44+2 -> 43 | B46: =B45 -> 330 | C46: =+C44+10 -> 210 | E46: High | F46: =IF((240+420)/2>($B46+$C46),($B46+$C46),(240+420)/2) -> 330 | G46: =C46+B46-F46 -> 210 | H46: =F46*$H$2 -> 1650 | I46: =$I$2*B46 -> 990 | J46: =$J$2*C46 -> 756 | K46: =-G46*3*0.5+0.5*G46 -> -210 | L46: =2*20 -> 40 | M46: =H46-SUM(I46:L46) -> 74 | N46: =M46*$N$2+M47*(1-$N$2) -> -38 | O46: =B46&"+"&C46 -> 330+210
B47: =B46 -> 330 | C47: =C46 -> 210 | E47: Low | F47: =IF((120+260)/2>($B47+$C47),($B47+$C47),(120+260)/2) -> 190 | G47: =C47+B47-F47 -> 350 | H47: =F47*$H$2 -> 950 | I47: =$I$2*B47 -> 990 | J47: =$J$2*C47 -> 756 | K47: =-G47*3*0.5+0.5*G47 -> -350 | L47: =2*20 -> 40 | M47: =H47-SUM(I47:L47) -> -486
A48: =A46+2 -> 45 | B48: =B47 -> 330 | C48: =+C46+10 -> 220 | E48: High | F48: =IF((240+420)/2>($B48+$C48),($B48+$C48),(240+420)/2) -> 330 | G48: =C48+B48-F48 -> 220 | H48: =F48*$H$2 -> 1650 | I48: =$I$2*B48 -> 990 | J48: =$J$2*C48 -> 792 | K48: =-G48*3*0.5+0.5*G48 -> -220 | L48: =2*20 -> 40 | M48: =H48-SUM(I48:L48) -> 48 | N48: =M48*$N$2+M49*(1-$N$2) -> -64 | O48: =B48&"+"&C48 -> 330+220
B49: =B48 -> 330 | C49: =C48 -> 220 | E49: Low | F49: =IF((120+260)/2>($B49+$C49),($B49+$C49),(120+260)/2) -> 190 | G49: =C49+B49-F49 -> 360 | H49: =F49*$H$2 -> 950 | I49: =$I$2*B49 -> 990 | J49: =$J$2*C49 -> 792 | K49: =-G49*3*0.5+0.5*G49 -> -360 | L49: =2*20 -> 40 | M49: =H49-SUM(I49:L49) -> -512
A50: =A48+2 -> 47 | B50: =B49 -> 330 | C50: =+C48+10 -> 230 | E50: High | F50: =IF((240+420)/2>($B50+$C50),($B50+$C50),(240+420)/2) -> 330 | G50: =C50+B50-F50 -> 230 | H50: =F50*$H$2 -> 1650 | I50: =$I$2*B50 -> 990 | J50: =$J$2*C50 -> 828 | K50: =-G50*3*0.5+0.5*G50 -> -230 | L50: =2*20 -> 40 | M50: =H50-SUM(I50:L50) -> 22 | N50: =M50*$N$2+M51*(1-$N$2) -> -90 | O50: =B50&"+"&C50 -> 330+230
B51: =B50 -> 330 | C51: =C50 -> 230 | E51: Low | F51: =IF((120+260)/2>($B51+$C51),($B51+$C51),(120+260)/2) -> 190 | G51: =C51+B51-F51 -> 370 | H51: =F51*$H$2 -> 950 | I51: =$I$2*B51 -> 990 | J51: =$J$2*C51 -> 828 | K51: =-G51*3*0.5+0.5*G51 -> -370 | L51: =2*20 -> 40 | M51: =H51-SUM(I51:L51) -> -538
A52: =A50+2 -> 49 | B52: =B51 -> 330 | C52: =+C50+10 -> 240 | E52: High | F52: =IF((240+420)/2>($B52+$C52),($B52+$C52),(240+420)/2) -> 330 | G52: =C52+B52-F52 -> 240 | H52: =F52*$H$2 -> 1650 | I52: =$I$2*B52 -> 990 | J52: =$J$2*C52 -> 864 | K52: =-G52*3*0.5+0.5*G52 -> -240 | L52: =2*20 -> 40 | M52: =H52-SUM(I52:L52) -> -4 | N52: =M52*$N$2+M53*(1-$N$2) -> -116 | O52: =B52&"+"&C52 -> 330+240
B53: =B52 -> 330 | C53: =C52 -> 240 | E53: Low | F53: =IF((120+260)/2>($B53+$C53),($B53+$C53),(120+260)/2) -> 190 | G53: =C53+B53-F53 -> 380 | H53: =F53*$H$2 -> 950 | I53: =$I$2*B53 -> 990 | J53: =$J$2*C53 -> 864 | K53: =-G53*3*0.5+0.5*G53 -> -380 | L53: =2*20 -> 40 | M53: =H53-SUM(I53:L53) -> -564
A54: =A52+2 -> 51 | B54: =B53 -> 330 | C54: =+C52+10 -> 250 | E54: High | F54: =IF((240+420)/2>($B54+$C54),($B54+$C54),(240+420)/2) -> 330 | G54: =C54+B54-F54 -> 250 | H54: =F54*$H$2 -> 1650 | I54: =$I$2*B54 -> 990 | J54: =$J$2*C54 -> 900 | K54: =-G54*3*0.5+0.5*G54 -> -250 | L54: =2*20 -> 40 | M54: =H54-SUM(I54:L54) -> -30 | N54: =M54*$N$2+M55*(1-$N$2) -> -142 | O54: =B54&"+"&C54 -> 330+250
B55: =B54 -> 330 | C55: =C54 -> 250 | E55: Low | F55: =IF((120+260)/2>($B55+$C55),($B55+$C55),(120+260)/2) -> 190 | G55: =C55+B55-F55 -> 390 | H55: =F55*$H$2 -> 950 | I55: =$I$2*B55 -> 990 | J55: =$J$2*C55 -> 900 | K55: =-G55*3*0.5+0.5*G55 -> -390 | L55: =2*20 -> 40 | M55: =H55-SUM(I55:L55) -> -590

Sheet iterations 8 (SL)
M1: Assumption
H2: 5 | I2: 3 | J2: 3.6 | M2: P(D=H⏐S=L) | N2: 0.4 | S2: P(S=H) | T2: 0.45
B3: Q0 | C3: Q1 | E3: Exp sales | G3: Exp left over | H3: Revenue | I3: Var cost | J3: Var cost | K3: refund cost | L3: ord cost | M3: Profit | N3: exp profit | O3: Q0+Q1 | P3: =N2*N4+'iterations 8 (SH)'!P4 -> 542.4 | S3: P(S=L) | T3: =1-T2 -> 0.55
A4: 1 | B4: 190 | C4: 0 | E4: High | F4: =IF((240+420)/2>($B4+$C4),($B4+$C4),(240+420)/2) -> 190 | G4: =C4+B4-F4 -> 0 | H4: =F4*$H$2 -> 950 | I4: =$I$2*B4 -> 570 | J4: =$J$2*C4 -> 0 | K4: =-G4*3*0.5+0.5*G4 -> 0 | L4: =2*20 -> 40 | M4: =H4-SUM(I4:L4) -> 340 | N4: =M4*$N$2+M5*(1-$N$2) -> 340 | O4: =B4&"+"&C4 -> 190+0 | S4: P(D=H⏐S=L) | T4: 0.4
B5: =B4 -> 190 | C5: =C4 -> 0 | E5: Low | F5: =IF((120+260)/2>($B5+$C5),($B5+$C5),(120+260)/2) -> 190 | G5: =C5+B5-F5 -> 0 | H5: =F5*$H$2 -> 950 | I5: =$I$2*B5 -> 570 | J5: =$J$2*C5 -> 0 | K5: =-G5*3*0.5+0.5*G5 -> 0 | L5: =2*20 -> 40 | M5: =H5-SUM(I5:L5) -> 340 | Q5: 170 | S5: P(D=L⏐S=L) | T5: =1-T4 -> 0.6
A6: =A4+2 -> 3 | B6: =B5 -> 190 | C6: =+C4+10 -> 10 | E6: High | F6: =IF((240+420)/2>($B6+$C6),($B6+$C6),(240+420)/2) -> 200 | G6: =C6+B6-F6 -> 0 | H6: =F6*$H$2 -> 1000 | I6: =$I$2*B6 -> 570 | J6: =$J$2*C6 -> 36 | K6: =-G6*3*0.5+0.5*G6 -> 0 | L6: =2*20 -> 40 | M6: =H6-SUM(I6:L6) -> 354 | N6: =M6*$N$2+M7*(1-$N$2) -> 330 | O6: =B6&"+"&C6 -> 190+10 | Q6: =Q5+10 -> 180 | S6: P(D=H⏐S=H) | T6: 0.8
B7: =B6 -> 190 | C7: =C6 -> 10 | E7: Low | F7: =IF((120+260)/2>($B7+$C7),($B7+$C7),(120+260)/2) -> 190 | G7: =C7+B7-F7 -> 10 | H7: =F7*$H$2 -> 950 | I7: =$I$2*B7 -> 570 | J7: =$J$2*C7 -> 36 | K7: =-G7*3*0.5+0.5*G7 -> -10 | L7: =2*20 -> 40 | M7: =H7-SUM(I7:L7) -> 314 | Q7: =Q6+10 -> 190 | S7: P(D=L⏐S=H) | T7: =1-T6 -> 0.2
A8: =A6+2 -> 5 | B8: =B7 -> 190 | C8: =+C6+10 -> 20 | E8: High | F8: =IF((240+420)/2>($B8+$C8),($B8+$C8),(240+420)/2) -> 210 | G8: =C8+B8-F8 -> 0 | H8: =F8*$H$2 -> 1050 | I8: =$I$2*B8 -> 570 | J8: =$J$2*C8 -> 72 | K8: =-G8*3*0.5+0.5*G8 -> 0 | L8: =2*20 -> 40 | M8: =H8-SUM(I8:L8) -> 368 | N8: =M8*$N$2+M9*(1-$N$2) -> 320 | O8: =B8&"+"&C8 -> 190+20 | Q8: =Q7+10 -> 200
B9: =B8 -> 190 | C9: =C8 -> 20 | E9: Low | F9: =IF((120+260)/2>($B9+$C9),($B9+$C9),(120+260)/2) -> 190 | G9: =C9+B9-F9 -> 20 | H9: =F9*$H$2 -> 950 | I9: =$I$2*B9 -> 570 | J9: =$J$2*C9 -> 72 | K9: =-G9*3*0.5+0.5*G9 -> -20 | L9: =2*20 -> 40 | M9: =H9-SUM(I9:L9) -> 288 | Q9: =Q8+10 -> 210
A10: =A8+2 -> 7 | B10: =B9 -> 190 | C10: =+C8+10 -> 30 | E10: High | F10: =IF((240+420)/2>($B10+$C10),($B10+$C10),(240+420)/2) -> 220 | G10: =C10+B10-F10 -> 0 | H10: =F10*$H$2 -> 1100 | I10: =$I$2*B10 -> 570 | J10: =$J$2*C10 -> 108 | K10: =-G10*3*0.5+0.5*G10 -> 0 | L10: =2*20 -> 40 | M10: =H10-SUM(I10:L10) -> 382 | N10: =M10*$N$2+M11*(1-$N$2) -> 310 | O10: =B10&"+"&C10 -> 190+30 | Q10: =Q9+10 -> 220
B11: =B10 -> 190 | C11: =C10 -> 30 | E11: Low | F11: =IF((120+260)/2>($B11+$C11),($B11+$C11),(120+260)/2) -> 190 | G11: =C11+B11-F11 -> 30 | H11: =F11*$H$2 -> 950 | I11: =$I$2*B11 -> 570 | J11: =$J$2*C11 -> 108 | K11: =-G11*3*0.5+0.5*G11 -> -30 | L11: =2*20 -> 40 | M11: =H11-SUM(I11:L11) -> 262 | Q11: =Q10+10 -> 230
A12: =A10+2 -> 9 | B12: =B11 -> 190 | C12: =+C10+10 -> 40 | E12: High | F12: =IF((240+420)/2>($B12+$C12),($B12+$C12),(240+420)/2) -> 230 | G12: =C12+B12-F12 -> 0 | H12: =F12*$H$2 -> 1150 | I12: =$I$2*B12 -> 570 | J12: =$J$2*C12 -> 144 | K12: =-G12*3*0.5+0.5*G12 -> 0 | L12: =2*20 -> 40 | M12: =H12-SUM(I12:L12) -> 396 | N12: =M12*$N$2+M13*(1-$N$2) -> 300 | O12: =B12&"+"&C12 -> 190+40 | Q12: =Q11+10 -> 240
B13: =B12 -> 190 | C13: =C12 -> 40 | E13: Low | F13: =IF((120+260)/2>($B13+$C13),($B13+$C13),(120+260)/2) -> 190 | G13: =C13+B13-F13 -> 40 | H13: =F13*$H$2 -> 950 | I13: =$I$2*B13 -> 570 | J13: =$J$2*C13 -> 144 | K13: =-G13*3*0.5+0.5*G13 -> -40 | L13: =2*20 -> 40 | M13: =H13-SUM(I13:L13) -> 236 | Q13: =Q12+10 -> 250 | S13: P(S=L⏐D=H)= | T13: P(D=H⏐S=L)P(S=L) | W13: =T4*T3/(T4*T3+T6*T2) -> 0.37931034
A14: =A12+2 -> 11 | B14: =B13 -> 190 | C14: =+C12+10 -> 50 | E14: High | F14: =IF((240+420)/2>($B14+$C14),($B14+$C14),(240+420)/2) -> 240 | G14: =C14+B14-F14 -> 0 | H14: =F14*$H$2 -> 1200 | I14: =$I$2*B14 -> 570 | J14: =$J$2*C14 -> 180 | K14: =-G14*3*0.5+0.5*G14 -> 0 | L14: =2*20 -> 40 | M14: =H14-SUM(I14:L14) -> 410 | N14: =M14*$N$2+M15*(1-$N$2) -> 290 | O14: =B14&"+"&C14 -> 190+50 | Q14: =Q13+10 -> 260 | T14: [P(D=H⏐S=L)P(S=L)+P(D=H⏐S=H)P(S=H)]
B15: =B14 -> 190 | C15: =C14 -> 50 | E15: Low | F15: =IF((120+260)/2>($B15+$C15),($B15+$C15),(120+260)/2) -> 190 | G15: =C15+B15-F15 -> 50 | H15: =F15*$H$2 -> 950 | I15: =$I$2*B15 -> 570 | J15: =$J$2*C15 -> 180 | K15: =-G15*3*0.5+0.5*G15 -> -50 | L15: =2*20 -> 40 | M15: =H15-SUM(I15:L15) -> 210 | Q15: =Q14+10 -> 270
A16: =A14+2 -> 13 | B16: =B15 -> 190 | C16: =+C14+10 -> 60 | E16: High | F16: =IF((240+420)/2>($B16+$C16),($B16+$C16),(240+420)/2) -> 250 | G16: =C16+B16-F16 -> 0 | H16: =F16*$H$2 -> 1250 | I16: =$I$2*B16 -> 570 | J16: =$J$2*C16 -> 216 | K16: =-G16*3*0.5+0.5*G16 -> 0 | L16: =2*20 -> 40 | M16: =H16-SUM(I16:L16) -> 424 | N16: =M16*$N$2+M17*(1-$N$2) -> 280 | O16: =B16&"+"&C16 -> 190+60 | Q16: =Q15+10 -> 280 | S16: P(S=H⏐D=H)= | W16: =1-W13 -> 0.62068966
B17: =B16 -> 190 | C17: =C16 -> 60 | E17: Low | F17: =IF((120+260)/2>($B17+$C17),($B17+$C17),(120+260)/2) -> 190 | G17: =C17+B17-F17 -> 60 | H17: =F17*$H$2 -> 950 | I17: =$I$2*B17 -> 570 | J17: =$J$2*C17 -> 216 | K17: =-G17*3*0.5+0.5*G17 -> -60 | L17: =2*20 -> 40 | M17: =H17-SUM(I17:L17) -> 184 | Q17: =Q16+10 -> 290
A18: =A16+2 -> 15 | B18: =B17 -> 190 | C18: =+C16+10 -> 70 | E18: High | F18: =IF((240+420)/2>($B18+$C18),($B18+$C18),(240+420)/2) -> 260 | G18: =C18+B18-F18 -> 0 | H18: =F18*$H$2 -> 1300 | I18: =$I$2*B18 -> 570 | J18: =$J$2*C18 -> 252 | K18: =-G18*3*0.5+0.5*G18 -> 0 | L18: =2*20 -> 40 | M18: =H18-SUM(I18:L18) -> 438 | N18: =M18*$N$2+M19*(1-$N$2) -> 270 | O18: =B18&"+"&C18 -> 190+70 | Q18: =Q17+10 -> 300 | S18: P(S=L⏐D=L)= | T18: P(D=L⏐S=L)P(S=L) | W18: =(T5*T3)/(T5*T3+T7*T2) -> 0.78571429
B19: =B18 -> 190 | C19: =C18 -> 70 | E19: Low | F19: =IF((120+260)/2>($B19+$C19),($B19+$C19),(120+260)/2) -> 190 | G19: =C19+B19-F19 -> 70 | H19: =F19*$H$2 -> 950 | I19: =$I$2*B19 -> 570 | J19: =$J$2*C19 -> 252 | K19: =-G19*3*0.5+0.5*G19 -> -70 | L19: =2*20 -> 40 | M19: =H19-SUM(I19:L19) -> 158 | Q19: =Q18+10 -> 310 | T19: [P(D=L⏐S=L)P(S=L)+P(D=L⏐S=H)P(S=H)]
A20: =A18+2 -> 17 | B20: =B19 -> 190 | C20: =+C18+10 -> 80 | E20: High | F20: =IF((240+420)/2>($B20+$C20),($B20+$C20),(240+420)/2) -> 270 | G20: =C20+B20-F20 -> 0 | H20: =F20*$H$2 -> 1350 | I20: =$I$2*B20 -> 570 | J20: =$J$2*C20 -> 288 | K20: =-G20*3*0.5+0.5*G20 -> 0 | L20: =2*20 -> 40 | M20: =H20-SUM(I20:L20) -> 452 | N20: =M20*$N$2+M21*(1-$N$2) -> 260 | O20: =B20&"+"&C20 -> 190+80 | Q20: =Q19+10 -> 320
B21: =B20 -> 190 | C21: =C20 -> 80 | E21: Low | F21: =IF((120+260)/2>($B21+$C21),($B21+$C21),(120+260)/2) -> 190 | G21: =C21+B21-F21 -> 80 | H21: =F21*$H$2 -> 950 | I21: =$I$2*B21 -> 570 | J21: =$J$2*C21 -> 288 | K21: =-G21*3*0.5+0.5*G21 -> -80 | L21: =2*20 -> 40 | M21: =H21-SUM(I21:L21) -> 132 | Q21: =Q20+10 -> 330 | S21: P(S=H⏐D=L)= | W21: =1-W18 -> 0.21428571
A22: =A20+2 -> 19 | B22: =B21 -> 190 | C22: =+C20+10 -> 90 | E22: High | F22: =IF((240+420)/2>($B22+$C22),($B22+$C22),(240+420)/2) -> 280 | G22: =C22+B22-F22 -> 0 | H22: =F22*$H$2 -> 1400 | I22: =$I$2*B22 -> 570 | J22: =$J$2*C22 -> 324 | K22: =-G22*3*0.5+0.5*G22 -> 0 | L22: =2*20 -> 40 | M22: =H22-SUM(I22:L22) -> 466 | N22: =M22*$N$2+M23*(1-$N$2) -> 250 | O22: =B22&"+"&C22 -> 190+90 | Q22: =Q21+10 -> 340
B23: =B22 -> 190 | C23: =C22 -> 90 | E23: Low | F23: =IF((120+260)/2>($B23+$C23),($B23+$C23),(120+260)/2) -> 190 | G23: =C23+B23-F23 -> 90 | H23: =F23*$H$2 -> 950 | I23: =$I$2*B23 -> 570 | J23: =$J$2*C23 -> 324 | K23: =-G23*3*0.5+0.5*G23 -> -90 | L23: =2*20 -> 40 | M23: =H23-SUM(I23:L23) -> 106 | Q23: =Q22+10 -> 350
A24: =A22+2 -> 21 | B24: =B23 -> 190 | C24: =+C22+10 -> 100 | E24: High | F24: =IF((240+420)/2>($B24+$C24),($B24+$C24),(240+420)/2) -> 290 | G24: =C24+B24-F24 -> 0 | H24: =F24*$H$2 -> 1450 | I24: =$I$2*B24 -> 570 | J24: =$J$2*C24 -> 360 | K24: =-G24*3*0.5+0.5*G24 -> 0 | L24: =2*20 -> 40 | M24: =H24-SUM(I24:L24) -> 480 | N24: =M24*$N$2+M25*(1-$N$2) -> 240 | O24: =B24&"+"&C24 -> 190+100 | Q24: =Q23+10 -> 360 | S24: P(D=H⏐S=L)= | T24: P(S=L⏐D=H)P(D=H) | W24: => | X24: =T4&"*"&"["&TEXT(W13,"0.00")&"P(D=H)"&"+"&TEXT(W18,"0.00")&"P(D=L)]=" -> 0.4*[0.38P(D=H)+0.79P(D=L)]= | Y24: =TEXT(W13,"0.00")&"P(D=H)" -> 0.38P(D=H)
B25: =B24 -> 190 | C25: =C24 -> 100 | E25: Low | F25: =IF((120+260)/2>($B25+$C25),($B25+$C25),(120+260)/2) -> 190 | G25: =C25+B25-F25 -> 100 | H25: =F25*$H$2 -> 950 | I25: =$I$2*B25 -> 570 | J25: =$J$2*C25 -> 360 | K25: =-G25*3*0.5+0.5*G25 -> -100 | L25: =2*20 -> 40 | M25: =H25-SUM(I25:L25) -> 80 | Q25: =Q24+10 -> 370 | T25: [P(S=L⏐D=H)P(D=H)+P(S=L⏐D=L)P(D=L)] | W25: => | X25: ="["&TEXT(W13,"0.00")&"P(D=H)"&"+"&TEXT(W18,"0.00")&"P(D=L)]=" -> [0.38P(D=H)+0.79P(D=L)]= | Y25: =TEXT(W13/T4,"0.00")&"P(D=H)" -> 0.95P(D=H)
A26: =A24+2 -> 23 | B26: =B25 -> 190 | C26: =+C24+10 -> 110 | E26: High | F26: =IF((240+420)/2>($B26+$C26),($B26+$C26),(240+420)/2) -> 300 | G26: =C26+B26-F26 -> 0 | H26: =F26*$H$2 -> 1500 | I26: =$I$2*B26 -> 570 | J26: =$J$2*C26 -> 396 | K26: =-G26*3*0.5+0.5*G26 -> 0 | L26: =2*20 -> 40 | M26: =H26-SUM(I26:L26) -> 494 | N26: =M26*$N$2+M27*(1-$N$2) -> 230 | O26: =B26&"+"&C26 -> 190+110 | Q26: =Q25+10 -> 380 | X26: ="["&TEXT(W18,"0.00")&"P(D=L)]=" -> [0.79P(D=L)]= | Y26: =TEXT(W13/T4-W13,"0.00")&"P(D=H)" -> 0.57P(D=H)
B27: =B26 -> 190 | C27: =C26 -> 110 | E27: Low | F27: =IF((120+260)/2>($B27+$C27),($B27+$C27),(120+260)/2) -> 190 | G27: =C27+B27-F27 -> 110 | H27: =F27*$H$2 -> 950 | I27: =$I$2*B27 -> 570 | J27: =$J$2*C27 -> 396 | K27: =-G27*3*0.5+0.5*G27 -> -110 | L27: =2*20 -> 40 | M27: =H27-SUM(I27:L27) -> 54 | Q27: =Q26+10 -> 390 | X27: ="P(D=L)=" -> P(D=L)= | Y27: =TEXT((W13/T4-W13)/W18,"0.00")&"P(D=H)" -> 0.72P(D=H)
A28: =A26+2 -> 25 | B28: =B27 -> 190 | C28: =+C26+10 -> 120 | E28: High | F28: =IF((240+420)/2>($B28+$C28),($B28+$C28),(240+420)/2) -> 310 | G28: =C28+B28-F28 -> 0 | H28: =F28*$H$2 -> 1550 | I28: =$I$2*B28 -> 570 | J28: =$J$2*C28 -> 432 | K28: =-G28*3*0.5+0.5*G28 -> 0 | L28: =2*20 -> 40 | M28: =H28-SUM(I28:L28) -> 508 | N28: =M28*$N$2+M29*(1-$N$2) -> 220 | O28: =B28&"+"&C28 -> 190+120 | Q28: =Q27+10 -> 400
B29: =B28 -> 190 | C29: =C28 -> 120 | E29: Low | F29: =IF((120+260)/2>($B29+$C29),($B29+$C29),(120+260)/2) -> 190 | G29: =C29+B29-F29 -> 120 | H29: =F29*$H$2 -> 950 | I29: =$I$2*B29 -> 570 | J29: =$J$2*C29 -> 432 | K29: =-G29*3*0.5+0.5*G29 -> -120 | L29: =2*20 -> 40 | M29: =H29-SUM(I29:L29) -> 28 | Q29: =Q28+10 -> 410 | X29: P(D=L)+P(D=H)= | Y29: 1
A30: =A28+2 -> 27 | B30: =B29 -> 190 | C30: =+C28+10 -> 130 | E30: High | F30: =IF((240+420)/2>($B30+$C30),($B30+$C30),(240+420)/2) -> 320 | G30: =C30+B30-F30 -> 0 | H30: =F30*$H$2 -> 1600 | I30: =$I$2*B30 -> 570 | J30: =$J$2*C30 -> 468 | K30: =-G30*3*0.5+0.5*G30 -> 0 | L30: =2*20 -> 40 | M30: =H30-SUM(I30:L30) -> 522 | N30: =M30*$N$2+M31*(1-$N$2) -> 210 | O30: =B30&"+"&C30 -> 190+130 | Q30: =Q29+10 -> 420 | X30: =TEXT((W13/T4-W13)/W18+1,"0.00")&"P(D=H)=" -> 1.72P(D=H)= | Y30: 1
B31: =B30 -> 190 | C31: =C30 -> 130 | E31: Low | F31: =IF((120+260)/2>($B31+$C31),($B31+$C31),(120+260)/2) -> 190 | G31: =C31+B31-F31 -> 130 | H31: =F31*$H$2 -> 950 | I31: =$I$2*B31 -> 570 | J31: =$J$2*C31 -> 468 | K31: =-G31*3*0.5+0.5*G31 -> -130 | L31: =2*20 -> 40 | M31: =H31-SUM(I31:L31) -> 2 | X31: P(D=H)= | Y31: =1/((W13/T4-W13)/W18+1) -> 0.58
A32: =A30+2 -> 29 | B32: =B31 -> 190 | C32: =+C30+10 -> 140 | E32: High | F32: =IF((240+420)/2>($B32+$C32),($B32+$C32),(240+420)/2) -> 330 | G32: =C32+B32-F32 -> 0 | H32: =F32*$H$2 -> 1650 | I32: =$I$2*B32 -> 570 | J32: =$J$2*C32 -> 504 | K32: =-G32*3*0.5+0.5*G32 -> 0 | L32: =2*20 -> 40 | M32: =H32-SUM(I32:L32) -> 536 | N32: =M32*$N$2+M33*(1-$N$2) -> 200 | O32: =B32&"+"&C32 -> 190+140 | X32: P(D=L)= | Y32: =1-Y31 -> 0.42
B33: =B32 -> 190 | C33: =C32 -> 140 | E33: Low | F33: =IF((120+260)/2>($B33+$C33),($B33+$C33),(120+260)/2) -> 190 | G33: =C33+B33-F33 -> 140 | H33: =F33*$H$2 -> 950 | I33: =$I$2*B33 -> 570 | J33: =$J$2*C33 -> 504 | K33: =-G33*3*0.5+0.5*G33 -> -140 | L33: =2*20 -> 40 | M33: =H33-SUM(I33:L33) -> -24
A34: =A32+2 -> 31 | B34: =B33 -> 190 | C34: =+C32+10 -> 150 | E34: High | F34: =IF((240+420)/2>($B34+$C34),($B34+$C34),(240+420)/2) -> 330 | G34: =C34+B34-F34 -> 10 | H34: =F34*$H$2 -> 1650 | I34: =$I$2*B34 -> 570 | J34: =$J$2*C34 -> 540 | K34: =-G34*3*0.5+0.5*G34 -> -10 | L34: =2*20 -> 40 | M34: =H34-SUM(I34:L34) -> 510 | N34: =M34*$N$2+M35*(1-$N$2) -> 174 | O34: =B34&"+"&C34 -> 190+150 | V34: VOSRC= | X34: =P3-'8'!K71 -> 189.8
B35: =B34 -> 190 | C35: =C34 -> 150 | E35: Low | F35: =IF((120+260)/2>($B35+$C35),($B35+$C35),(120+260)/2) -> 190 | G35: =C35+B35-F35 -> 150 | H35: =F35*$H$2 -> 950 | I35: =$I$2*B35 -> 570 | J35: =$J$2*C35 -> 540 | K35: =-G35*3*0.5+0.5*G35 -> -150 | L35: =2*20 -> 40 | M35: =H35-SUM(I35:L35) -> -50
A36: =A34+2 -> 33 | B36: =B35 -> 190 | C36: =+C34+10 -> 160 | E36: High | F36: =IF((240+420)/2>($B36+$C36),($B36+$C36),(240+420)/2) -> 330 | G36: =C36+B36-F36 -> 20 | H36: =F36*$H$2 -> 1650 | I36: =$I$2*B36 -> 570 | J36: =$J$2*C36 -> 576 | K36: =-G36*3*0.5+0.5*G36 -> -20 | L36: =2*20 -> 40 | M36: =H36-SUM(I36:L36) -> 484 | N36: =M36*$N$2+M37*(1-$N$2) -> 148 | O36: =B36&"+"&C36 -> 190+160
B37: =B36 -> 190 | C37: =C36 -> 160 | E37: Low | F37: =IF((120+260)/2>($B37+$C37),($B37+$C37),(120+260)/2) -> 190 | G37: =C37+B37-F37 -> 160 | H37: =F37*$H$2 -> 950 | I37: =$I$2*B37 -> 570 | J37: =$J$2*C37 -> 576 | K37: =-G37*3*0.5+0.5*G37 -> -160 | L37: =2*20 -> 40 | M37: =H37-SUM(I37:L37) -> -76
A38: =A36+2 -> 35 | B38: =B37 -> 190 | C38: =+C36+10 -> 170 | E38: High | F38: =IF((240+420)/2>($B38+$C38),($B38+$C38),(240+420)/2) -> 330 | G38: =C38+B38-F38 -> 30 | H38: =F38*$H$2 -> 1650 | I38: =$I$2*B38 -> 570 | J38: =$J$2*C38 -> 612 | K38: =-G38*3*0.5+0.5*G38 -> -30 | L38: =2*20 -> 40 | M38: =H38-SUM(I38:L38) -> 458 | N38: =M38*$N$2+M39*(1-$N$2) -> 122 | O38: =B38&"+"&C38 -> 190+170
B39: =B38 -> 190 | C39: =C38 -> 170 | E39: Low | F39: =IF((120+260)/2>($B39+$C39),($B39+$C39),(120+260)/2) -> 190 | G39: =C39+B39-F39 -> 170 | H39: =F39*$H$2 -> 950 | I39: =$I$2*B39 -> 570 | J39: =$J$2*C39 -> 612 | K39: =-G39*3*0.5+0.5*G39 -> -170 | L39: =2*20 -> 40 | M39: =H39-SUM(I39:L39) -> -102
A40: =A38+2 -> 37 | B40: =B39 -> 190 | C40: =+C38+10 -> 180 | E40: High | F40: =IF((240+420)/2>($B40+$C40),($B40+$C40),(240+420)/2) -> 330 | G40: =C40+B40-F40 -> 40 | H40: =F40*$H$2 -> 1650 | I40: =$I$2*B40 -> 570 | J40: =$J$2*C40 -> 648 | K40: =-G40*3*0.5+0.5*G40 -> -40 | L40: =2*20 -> 40 | M40: =H40-SUM(I40:L40) -> 432 | N40: =M40*$N$2+M41*(1-$N$2) -> 96 | O40: =B40&"+"&C40 -> 190+180
B41: =B40 -> 190 | C41: =C40 -> 180 | E41: Low | F41: =IF((120+260)/2>($B41+$C41),($B41+$C41),(120+260)/2) -> 190 | G41: =C41+B41-F41 -> 180 | H41: =F41*$H$2 -> 950 | I41: =$I$2*B41 -> 570 | J41: =$J$2*C41 -> 648 | K41: =-G41*3*0.5+0.5*G41 -> -180 | L41: =2*20 -> 40 | M41: =H41-SUM(I41:L41) -> -128
A42: =A40+2 -> 39 | B42: =B41 -> 190 | C42: =+C40+10 -> 190 | E42: High | F42: =IF((240+420)/2>($B42+$C42),($B42+$C42),(240+420)/2) -> 330 | G42: =C42+B42-F42 -> 50 | H42: =F42*$H$2 -> 1650 | I42: =$I$2*B42 -> 570 | J42: =$J$2*C42 -> 684 | K42: =-G42*3*0.5+0.5*G42 -> -50 | L42: =2*20 -> 40 | M42: =H42-SUM(I42:L42) -> 406 | N42: =M42*$N$2+M43*(1-$N$2) -> 70 | O42: =B42&"+"&C42 -> 190+190
B43: =B42 -> 190 | C43: =C42 -> 190 | E43: Low | F43: =IF((120+260)/2>($B43+$C43),($B43+$C43),(120+260)/2) -> 190 | G43: =C43+B43-F43 -> 190 | H43: =F43*$H$2 -> 950 | I43: =$I$2*B43 -> 570 | J43: =$J$2*C43 -> 684 | K43: =-G43*3*0.5+0.5*G43 -> -190 | L43: =2*20 -> 40 | M43: =H43-SUM(I43:L43) -> -154
A44: =A42+2 -> 41 | B44: =B43 -> 190 | C44: =+C42+10 -> 200 | E44: High | F44: =IF((240+420)/2>($B44+$C44),($B44+$C44),(240+420)/2) -> 330 | G44: =C44+B44-F44 -> 60 | H44: =F44*$H$2 -> 1650 | I44: =$I$2*B44 -> 570 | J44: =$J$2*C44 -> 720 | K44: =-G44*3*0.5+0.5*G44 -> -60 | L44: =2*20 -> 40 | M44: =H44-SUM(I44:L44) -> 380 | N44: =M44*$N$2+M45*(1-$N$2) -> 44 | O44: =B44&"+"&C44 -> 190+200
B45: =B44 -> 190 | C45: =C44 -> 200 | E45: Low | F45: =IF((120+260)/2>($B45+$C45),($B45+$C45),(120+260)/2) -> 190 | G45: =C45+B45-F45 -> 200 | H45: =F45*$H$2 -> 950 | I45: =$I$2*B45 -> 570 | J45: =$J$2*C45 -> 720 | K45: =-G45*3*0.5+0.5*G45 -> -200 | L45: =2*20 -> 40 | M45: =H45-SUM(I45:L45) -> -180
A46: =A44+2 -> 43 | B46: =B45 -> 190 | C46: =+C44+10 -> 210 | E46: High | F46: =IF((240+420)/2>($B46+$C46),($B46+$C46),(240+420)/2) -> 330 | G46: =C46+B46-F46 -> 70 | H46: =F46*$H$2 -> 1650 | I46: =$I$2*B46 -> 570 | J46: =$J$2*C46 -> 756 | K46: =-G46*3*0.5+0.5*G46 -> -70 | L46: =2*20 -> 40 | M46: =H46-SUM(I46:L46) -> 354 | N46: =M46*$N$2+M47*(1-$N$2) -> 18 | O46: =B46&"+"&C46 -> 190+210
B47: =B46 -> 190 | C47: =C46 -> 210 | E47: Low | F47: =IF((120+260)/2>($B47+$C47),($B47+$C47),(120+260)/2) -> 190 | G47: =C47+B47-F47 -> 210 | H47: =F47*$H$2 -> 950 | I47: =$I$2*B47 -> 570 | J47: =$J$2*C47 -> 756 | K47: =-G47*3*0.5+0.5*G47 -> -210 | L47: =2*20 -> 40 | M47: =H47-SUM(I47:L47) -> -206
A48: =A46+2 -> 45 | B48: =B47 -> 190 | C48: =+C46+10 -> 220 | E48: High | F48: =IF((240+420)/2>($B48+$C48),($B48+$C48),(240+420)/2) -> 330 | G48: =C48+B48-F48 -> 80 | H48: =F48*$H$2 -> 1650 | I48: =$I$2*B48 -> 570 | J48: =$J$2*C48 -> 792 | K48: =-G48*3*0.5+0.5*G48 -> -80 | L48: =2*20 -> 40 | M48: =H48-SUM(I48:L48) -> 328 | N48: =M48*$N$2+M49*(1-$N$2) -> -8 | O48: =B48&"+"&C48 -> 190+220
B49: =B48 -> 190 | C49: =C48 -> 220 | E49: Low | F49: =IF((120+260)/2>($B49+$C49),($B49+$C49),(120+260)/2) -> 190 | G49: =C49+B49-F49 -> 220 | H49: =F49*$H$2 -> 950 | I49: =$I$2*B49 -> 570 | J49: =$J$2*C49 -> 792 | K49: =-G49*3*0.5+0.5*G49 -> -220 | L49: =2*20 -> 40 | M49: =H49-SUM(I49:L49) -> -232
A50: =A48+2 -> 47 | B50: =B49 -> 190 | C50: =+C48+10 -> 230 | E50: High | F50: =IF((240+420)/2>($B50+$C50),($B50+$C50),(240+420)/2) -> 330 | G50: =C50+B50-F50 -> 90 | H50: =F50*$H$2 -> 1650 | I50: =$I$2*B50 -> 570 | J50: =$J$2*C50 -> 828 | K50: =-G50*3*0.5+0.5*G50 -> -90 | L50: =2*20 -> 40 | M50: =H50-SUM(I50:L50) -> 302 | N50: =M50*$N$2+M51*(1-$N$2) -> -34 | O50: =B50&"+"&C50 -> 190+230
B51: =B50 -> 190 | C51: =C50 -> 230 | E51: Low | F51: =IF((120+260)/2>($B51+$C51),($B51+$C51),(120+260)/2) -> 190 | G51: =C51+B51-F51 -> 230 | H51: =F51*$H$2 -> 950 | I51: =$I$2*B51 -> 570 | J51: =$J$2*C51 -> 828 | K51: =-G51*3*0.5+0.5*G51 -> -230 | L51: =2*20 -> 40 | M51: =H51-SUM(I51:L51) -> -258
A52: =A50+2 -> 49 | B52: =B51 -> 190 | C52: =+C50+10 -> 240 | E52: High | F52: =IF((240+420)/2>($B52+$C52),($B52+$C52),(240+420)/2) -> 330 | G52: =C52+B52-F52 -> 100 | H52: =F52*$H$2 -> 1650 | I52: =$I$2*B52 -> 570 | J52: =$J$2*C52 -> 864 | K52: =-G52*3*0.5+0.5*G52 -> -100 | L52: =2*20 -> 40 | M52: =H52-SUM(I52:L52) -> 276 | N52: =M52*$N$2+M53*(1-$N$2) -> -60 | O52: =B52&"+"&C52 -> 190+240
B53: =B52 -> 190 | C53: =C52 -> 240 | E53: Low | F53: =IF((120+260)/2>($B53+$C53),($B53+$C53),(120+260)/2) -> 190 | G53: =C53+B53-F53 -> 240 | H53: =F53*$H$2 -> 950 | I53: =$I$2*B53 -> 570 | J53: =$J$2*C53 -> 864 | K53: =-G53*3*0.5+0.5*G53 -> -240 | L53: =2*20 -> 40 | M53: =H53-SUM(I53:L53) -> -284
A54: =A52+2 -> 51 | B54: =B53 -> 190 | C54: =+C52+10 -> 250 | E54: High | F54: =IF((240+420)/2>($B54+$C54),($B54+$C54),(240+420)/2) -> 330 | G54: =C54+B54-F54 -> 110 | H54: =F54*$H$2 -> 1650 | I54: =$I$2*B54 -> 570 | J54: =$J$2*C54 -> 900 | K54: =-G54*3*0.5+0.5*G54 -> -110 | L54: =2*20 -> 40 | M54: =H54-SUM(I54:L54) -> 250 | N54: =M54*$N$2+M55*(1-$N$2) -> -86 | O54: =B54&"+"&C54 -> 190+250
B55: =B54 -> 190 | C55: =C54 -> 250 | E55: Low | F55: =IF((120+260)/2>($B55+$C55),($B55+$C55),(120+260)/2) -> 190 | G55: =C55+B55-F55 -> 250 | H55: =F55*$H$2 -> 950 | I55: =$I$2*B55 -> 570 | J55: =$J$2*C55 -> 900 | K55: =-G55*3*0.5+0.5*G55 -> -250 | L55: =2*20 -> 40 | M55: =H55-SUM(I55:L55) -> -310
